rtl/edge_analytics.v
`timescale 1ns / 1ps

module edge_analytics #(
    parameter WINDOW_SIZE_LOG2 = 4,   // 16 samples window
    parameter DEFAULT_T_LOW = 16'd50,
    parameter DEFAULT_T_HIGH = 16'd200
)(
    input  wire        clk,
    input  wire        rst_n,

    // CSR Interface
    input  wire        csr_en,
    input  wire [1:0]  csr_force_mode,
    input  wire [15:0] csr_t_low,
    input  wire [15:0] csr_t_high,

    // Data Path Interface
    input  wire [15:0] sample_in,
    input  wire        valid_in,
    input  wire        ready_in,

    output reg  [15:0] data_out,
    output reg         valid_out,
    output wire        ready_out,
    output reg  [1:0]  mode_out,
    output reg  [3:0]  q_out
);

    assign ready_out = !valid_out || ready_in;

    localparam WINDOW_SIZE = 1 << WINDOW_SIZE_LOG2;

    // Internal state
    reg [15:0] window [0:WINDOW_SIZE-1];
    reg [WINDOW_SIZE_LOG2-1:0] w_ptr;
    
    // Accumulators for mean calculation
    reg [31:0] sum;
    reg [15:0] current_mean;

    // MAD calculation state
    reg [15:0] current_mad;
    reg        window_seeded;

    integer i;

    // Thresholds
    wire [15:0] t_low = csr_t_low ? csr_t_low : DEFAULT_T_LOW;
    wire [15:0] t_high = csr_t_high ? csr_t_high : DEFAULT_T_HIGH;

    // --- Combinational MAD calculation (separated from clocked block) ---
    // Uses the UPDATED mean (computed combinationally) so MAD tracks the 
    // current window, not the stale one-cycle-old mean.
    wire [31:0] updated_sum = sum + sample_in - window[w_ptr];
    wire [15:0] updated_mean = updated_sum >> WINDOW_SIZE_LOG2;

    reg [31:0] mad_sum_comb;
    integer j;
    always @(*) begin
        mad_sum_comb = 0;
        for (j = 0; j < WINDOW_SIZE; j = j + 1) begin
            if (window[j] > updated_mean)
                mad_sum_comb = mad_sum_comb + (window[j] - updated_mean);
            else
                mad_sum_comb = mad_sum_comb + (updated_mean - window[j]);
        end
    end

    always @(posedge clk or negedge rst_n) begin
        if (!rst_n) begin
            for (i = 0; i < WINDOW_SIZE; i = i + 1) begin
                window[i] <= 16'd0;
            end
            w_ptr <= 0;
            sum <= 32'd0;
            current_mean <= 16'd0;
            current_mad <= 16'd0;
            window_seeded <= 1'b0;
            
            data_out <= 16'd0;
            valid_out <= 1'b0;
            mode_out <= 2'b00;
            q_out <= 4'd0;
        end else if (ready_out) begin
            valid_out <= 1'b0;
            
            if (valid_in) begin
                valid_out <= 1'b1;

                if (!window_seeded) begin
                    for (i = 0; i < WINDOW_SIZE; i = i + 1) begin
                        window[i] <= sample_in;
                    end
                    w_ptr <= 1;
                    sum <= {16'd0, sample_in} << WINDOW_SIZE_LOG2;
                    current_mean <= sample_in;
                    current_mad <= 16'd0;
                    window_seeded <= 1'b1;

                    if (csr_en) begin
                         mode_out <= csr_force_mode;
                         case (csr_force_mode)
                             2'b00: q_out <= 4'd0;
                             2'b01: q_out <= 4'd2;
                             2'b10: q_out <= 4'd4;
                             default: q_out <= 4'd0;
                         endcase
                    end else begin
                        mode_out <= 2'b01;
                        q_out <= 4'd2;
                    end
                end else begin
                    // Update window and sum
                    sum <= updated_sum;
                    window[w_ptr] <= sample_in;
                    w_ptr <= w_ptr + 1;
                    
                    // Use the combinationally updated mean
                    current_mean <= updated_mean;
                    
                    // MAD uses the combinational result from the always @(*) block
                    current_mad <= mad_sum_comb >> WINDOW_SIZE_LOG2;

                    // Mode decision:
                    // Stable/healthy telemetry is quantised to save bandwidth.
                    // Varying or anomalous telemetry is preserved losslessly.
                    if (csr_en) begin
                         mode_out <= csr_force_mode;
                         case (csr_force_mode)
                             2'b00: q_out <= 4'd0;
                             2'b01: q_out <= 4'd2; // Default light lossy
                             2'b10: q_out <= 4'd4; // Default heavy lossy
                             default: q_out <= 4'd0;
                         endcase
                    end else begin
                        if ((mad_sum_comb >> WINDOW_SIZE_LOG2) < t_low) begin
                            mode_out <= 2'b01; // Stable: lossy compression
                            q_out <= 4'd2;
                        end else if ((mad_sum_comb >> WINDOW_SIZE_LOG2) < t_high) begin
                            mode_out <= 2'b00; // Varying: preserve detail
                            q_out <= 4'd0;
                        end else begin
                            mode_out <= 2'b00; // Anomaly: preserve full precision
                            q_out <= 4'd0; 
                        end
                    end
                end

                data_out <= sample_in;
            end
        end
    end

    integer ea_valid_out_cnt = 0;
    always @(posedge clk) begin
        if (valid_out) ea_valid_out_cnt = ea_valid_out_cnt + 1;
    end

endmodule

tb/tb_edge_analytics.v
`timescale 1ns / 1ps

module tb_edge_analytics;

    reg clk;
    reg rst_n;
    reg csr_en;
    reg [1:0] csr_force_mode;
    reg [15:0] csr_t_low;
    reg [15:0] csr_t_high;
    reg [15:0] sample_in;
    reg valid_in;

    wire [15:0] data_out;
    wire valid_out;
    wire [1:0] mode_out;
    wire [3:0] q_out;

    edge_analytics uut (
        .clk(clk),
        .rst_n(rst_n),
        .csr_en(csr_en),
        .csr_force_mode(csr_force_mode),
        .csr_t_low(csr_t_low),
        .csr_t_high(csr_t_high),
        .sample_in(sample_in),
        .valid_in(valid_in),
        .ready_in(1'b1),
        .data_out(data_out),
        .valid_out(valid_out),
        .ready_out(),
        .mode_out(mode_out),
        .q_out(q_out)
    );

    always #5 clk = ~clk;

    integer i;

    initial begin
        $dumpfile("sim/edge_analytics.vcd");
        $dumpvars(0, tb_edge_analytics);

        clk = 0;
        rst_n = 0;
        csr_en = 0;
        csr_force_mode = 0;
        csr_t_low = 50;
        csr_t_high = 200;
        sample_in = 0;
        valid_in = 0;

        #20 rst_n = 1;

        $display("Testing stable signal (bandwidth-saving lossy)...");
        for (i = 0; i < 20; i = i + 1) begin
            @(posedge clk);
            sample_in <= 1000;
            valid_in <= 1;
        end

        @(posedge clk);
        valid_in <= 0;
        #20;
        if (mode_out !== 2'b01 || q_out !== 4'd2) $display("FAIL: Expected Mode 01 / Q=2 (stable lossy)");
        else $display("PASS: Mode 01 / Q=2 correctly selected.");

        $display("Testing moderately volatile signal (lossless detail preserve)...");
        for (i = 0; i < 20; i = i + 1) begin
            @(posedge clk);
            sample_in <= (i % 2 == 0) ? 1000 : 1150; // Moderate swing
            valid_in <= 1;
        end
        
        @(posedge clk);
        valid_in <= 0;
        #20;
        if (mode_out !== 2'b00 || q_out !== 4'd0) $display("FAIL: Expected Mode 00 / Q=0 (varying lossless)");
        else $display("PASS: Mode 00 / Q=0 correctly selected.");

        $display("Testing highly volatile signal (Anomaly)...");
        for (i = 0; i < 20; i = i + 1) begin
            @(posedge clk);
            sample_in <= (i % 2 == 0) ? 1000 : 2000; // Big swing
            valid_in <= 1;
        end
        
        @(posedge clk);
        valid_in <= 0;
        #20;
        if (mode_out !== 2'b00 || q_out !== 4'd0) $display("FAIL: Expected Mode 00 / Q=0 (anomaly lossless)");
        else $display("PASS: Mode 00 / Q=0 anomaly correctly selected.");


        #50 $finish;
    end

endmodule

sim/edge_analytics.vcd
$date
	Mon Apr 27 16:20:15 2026
$end
$version
	Icarus Verilog
$end
$timescale
	1ps
$end
$scope module tb_edge_analytics $end
$var wire 1 ! valid_out $end
$var wire 4 " q_out [3:0] $end
$var wire 2 # mode_out [1:0] $end
$var wire 16 $ data_out [15:0] $end
$var reg 1 % clk $end
$var reg 1 & csr_en $end
$var reg 2 ' csr_force_mode [1:0] $end
$var reg 16 ( csr_t_high [15:0] $end
$var reg 16 ) csr_t_low [15:0] $end
$var reg 1 * rst_n $end
$var reg 16 + sample_in [15:0] $end
$var reg 1 , valid_in $end
$var integer 32 - i [31:0] $end
$scope module uut $end
$var wire 1 % clk $end
$var wire 1 & csr_en $end
$var wire 2 . csr_force_mode [1:0] $end
$var wire 16 / csr_t_high [15:0] $end
$var wire 16 0 csr_t_low [15:0] $end
$var wire 1 1 ready_in $end
$var wire 1 2 ready_out $end
$var wire 1 * rst_n $end
$var wire 16 3 sample_in [15:0] $end
$var wire 1 , valid_in $end
$var wire 32 4 updated_sum [31:0] $end
$var wire 16 5 updated_mean [15:0] $end
$var wire 16 6 t_low [15:0] $end
$var wire 16 7 t_high [15:0] $end
$var parameter 16 8 DEFAULT_T_HIGH $end
$var parameter 16 9 DEFAULT_T_LOW $end
$var parameter 36 : WINDOW_SIZE $end
$var parameter 32 ; WINDOW_SIZE_LOG2 $end
$var reg 16 < current_mad [15:0] $end
$var reg 16 = current_mean [15:0] $end
$var reg 16 > data_out [15:0] $end
$var reg 32 ? mad_sum_comb [31:0] $end
$var reg 2 @ mode_out [1:0] $end
$var reg 4 A q_out [3:0] $end
$var reg 32 B sum [31:0] $end
$var reg 1 ! valid_out $end
$var reg 4 C w_ptr [3:0] $end
$var reg 1 D window_seeded $end
$var integer 32 E ea_valid_out_cnt [31:0] $end
$var integer 32 F i [31:0] $end
$var integer 32 G j [31:0] $end
$upscope $end
$upscope $end
$enddefinitions $end
$comment Show the parameter values. $end
$dumpall
b100 ;
b10000 :
b110010 9
b11001000 8
$end
#0
$dumpvars
b10000 G
b10000 F
b0 E
0D
b0 C
b0 B
b0 A
b0 @
b0 ?
b0 >
b0 =
b0 <
b11001000 7
b110010 6
b0 5
b0 4
b0 3
12
11
b110010 0
b11001000 /
b0 .
bx -
0,
b0 +
0*
b110010 )
b11001000 (
b0 '
0&
0%
b0 $
b0 #
b0 "
0!
$end
#5000
b10000 F
1%
#10000
0%
#15000
b10000 F
1%
#20000
0%
b0 -
1*
#25000
b1111100000 ?
b10000 G
b111110 5
1,
b1111101000 4
b1111101000 +
b1111101000 3
b1 -
1%
#30000
0%
#35000
b1111101000 5
b10000 G
b0 ?
b1111101000 $
b1111101000 >
b10 "
b10 A
b1 #
b1 @
1D
b1111101000 =
b11111010000000 B
b1 C
b11111010000000 4
1!
b10 -
b10000 F
1%
#40000
0%
#45000
b10 C
1!
b1 E
b11 -
1%
#50000
0%
#55000
b11 C
1!
b100 -
b10 E
1%
#60000
0%
#65000
b100 C
1!
b11 E
b101 -
1%
#70000
0%
#75000
b101 C
1!
b110 -
b100 E
1%
#80000
0%
#85000
b110 C
1!
b101 E
b111 -
1%
#90000
0%
#95000
b111 C
1!
b1000 -
b110 E
1%
#100000
0%
#105000
b1000 C
1!
b111 E
b1001 -
1%
#110000
0%
#115000
b1001 C
1!
b1010 -
b1000 E
1%
#120000
0%
#125000
b1010 C
1!
b1001 E
b1011 -
1%
#130000
0%
#135000
b1011 C
1!
b1100 -
b1010 E
1%
#140000
0%
#145000
b1100 C
1!
b1011 E
b1101 -
1%
#150000
0%
#155000
b1101 C
1!
b1110 -
b1100 E
1%
#160000
0%
#165000
b1110 C
1!
b1101 E
b1111 -
1%
#170000
0%
#175000
b1111 C
1!
b10000 -
b1110 E
1%
#180000
0%
#185000
b0 C
1!
b1111 E
b10001 -
1%
#190000
0%
#195000
b1 C
1!
b10010 -
b10000 E
1%
#200000
0%
#205000
b10 C
1!
b10001 E
b10011 -
1%
#210000
0%
#215000
b11 C
1!
b10100 -
b10010 E
1%
#220000
0%
#225000
0,
b100 C
1!
b10011 E
1%
#230000
0%
#235000
0!
b10100 E
1%
#240000
0%
#245000
1,
1%
b1 -
#250000
0%
#255000
b10010000 ?
b10000 G
b1111110001 5
b11111100010110 4
b10001111110 +
b10001111110 3
b101 C
1!
b10 -
1%
#260000
0%
#265000
b10000 G
b100010100 ?
b1111101000 +
b1111101000 3
b10001111110 $
b10001111110 >
b1001 <
b1111110001 =
b110 C
b11111100010110 4
b11111100010110 B
1!
b10101 E
b11 -
1%
#270000
0%
#275000
b10000 G
b110010010 ?
b1111111010 5
b11111110101100 4
b10001111110 +
b10001111110 3
b1111101000 $
b1111101000 >
b10001 <
b111 C
1!
b100 -
b10110 E
1%
#280000
0%
#285000
b10000 G
b1000000100 ?
b1111101000 +
b1111101000 3
b10001111110 $
b10001111110 >
b11001 <
b1111111010 =
b1000 C
b11111110101100 4
b11111110101100 B
1!
b10111 E
b101 -
1%
#290000
0%
#295000
b10000 G
b1001111100 ?
b10000000100 5
b100000001000010 4
b10001111110 +
b10001111110 3
b1111101000 $
b1111101000 >
b100000 <
b1001 C
1!
b110 -
b11000 E
1%
#300000
0%
#305000
b10000 G
b1011011010 ?
b1111101000 +
b1111101000 3
b10001111110 $
b10001111110 >
b100111 <
b10000000100 =
b1010 C
b100000001000010 4
b100000001000010 B
1!
b11001 E
b111 -
1%
#310000
0%
#315000
b10000 G
b1100110100 ?
b10000001101 5
b100000011011000 4
b10001111110 +
b10001111110 3
b1111101000 $
b1111101000 >
b101101 <
b1011 C
1!
b1000 -
b11010 E
1%
#320000
0%
#325000
b10000 G
b1110000000 ?
b1111101000 +
b1111101000 3
b10001111110 $
b10001111110 >
b0 "
b0 A
b0 #
b0 @
b110011 <
b10000001101 =
b1100 C
b100000011011000 4
b100000011011000 B
1!
b11011 E
b1001 -
1%
#330000
0%
#335000
b10000 G
b1111001000 ?
b10000010110 5
b100000101101110 4
b10001111110 +
b10001111110 3
b1111101000 $
b1111101000 >
b111000 <
b1101 C
1!
b1010 -
b11100 E
1%
#340000
0%
#345000
b10000 G
b10000000010 ?
b1111101000 +
b1111101000 3
b10001111110 $
b10001111110 >
b111100 <
b10000010110 =
b1110 C
b100000101101110 4
b100000101101110 B
1!
b11101 E
b1011 -
1%
#350000
0%
#355000
b10000 G
b10000111110 ?
b10000100000 5
b100001000000100 4
b10001111110 +
b10001111110 3
b1111101000 $
b1111101000 >
b1000000 <
b1111 C
1!
b1100 -
b11110 E
1%
#360000
0%
#365000
b10000 G
b10001100100 ?
b1111101000 +
b1111101000 3
b10001111110 $
b10001111110 >
b1000011 <
b10000100000 =
b0 C
b100001000000100 4
b100001000000100 B
1!
b11111 E
b1101 -
1%
#370000
0%
#375000
b10000 G
b10010001000 ?
b10000101001 5
b100001010011010 4
b10001111110 +
b10001111110 3
b1111101000 $
b1111101000 >
b1000110 <
b1 C
1!
b1110 -
b100000 E
1%
#380000
0%
#385000
b10000 G
b10010011100 ?
b1111101000 +
b1111101000 3
b10001111110 $
b10001111110 >
b1001000 <
b10000101001 =
b10 C
b100001010011010 4
b100001010011010 B
1!
b100001 E
b1111 -
1%
#390000
0%
#395000
b10000 G
b10010110000 ?
b10000110011 5
b100001100110000 4
b10001111110 +
b10001111110 3
b1111101000 $
b1111101000 >
b1001001 <
b11 C
1!
b10000 -
b100010 E
1%
#400000
0%
#405000
b10000 G
b10010110000 ?
b1111101000 +
b1111101000 3
b10001111110 $
b10001111110 >
b1001011 <
b10000110011 =
b100 C
b100001100110000 4
b100001100110000 B
1!
b100011 E
b10001 -
1%
#410000
0%
#415000
b10001111110 +
b10001111110 3
b1111101000 $
b1111101000 >
b100001100110000 4
b101 C
1!
b10010 -
b100100 E
1%
#420000
0%
#425000
b1111101000 +
b1111101000 3
b10001111110 $
b10001111110 >
b100001100110000 4
b110 C
1!
b100101 E
b10011 -
1%
#430000
0%
#435000
b10001111110 +
b10001111110 3
b1111101000 $
b1111101000 >
b100001100110000 4
b111 C
1!
b10100 -
b100110 E
1%
#440000
0%
#445000
b10000 G
b10010110000 ?
b10000111100 5
0,
b10001111110 $
b10001111110 >
b100001111000110 4
b1000 C
1!
b100111 E
1%
#450000
0%
#455000
0!
b101000 E
1%
#460000
0%
#465000
b10000 G
b10010110000 ?
b10000110011 5
1,
b100001100110000 4
b1111101000 +
b1111101000 3
1%
b1 -
#470000
0%
#475000
b10000 G
b10010110000 ?
b10001101000 5
b11111010000 +
b11111010000 3
b1111101000 $
b1111101000 >
b100011010000010 4
b1001 C
1!
b10 -
1%
#480000
0%
#485000
b10000 G
b100000000010 ?
b1111101000 +
b1111101000 3
b11111010000 $
b11111010000 >
b10001101000 =
b1010 C
b100011010000010 4
b100011010000010 B
1!
b101001 E
b11 -
1%
#490000
0%
#495000
b10000 G
b100110110100 ?
b10010011101 5
b11111010000 +
b11111010000 3
b1111101000 $
b1111101000 >
b10000000 <
b100100111010100 4
b1011 C
1!
b100 -
b101010 E
1%
#500000
0%
#505000
b10000 G
b110011001000 ?
b1111101000 +
b1111101000 3
b11111010000 $
b11111010000 >
b10011011 <
b10010011101 =
b1100 C
b100100111010100 4
b100100111010100 B
1!
b101011 E
b101 -
1%
#510000
0%
#515000
b10000 G
b111101000100 ?
b10011010010 5
b11111010000 +
b11111010000 3
b1111101000 $
b1111101000 >
b11001100 <
b100110100100110 4
b1101 C
1!
b110 -
b101100 E
1%
#520000
0%
#525000
b10000 G
b1000111101110 ?
b1111101000 +
b1111101000 3
b11111010000 $
b11111010000 >
b11110100 <
b10011010010 =
b1110 C
b100110100100110 4
b100110100100110 B
1!
b101101 E
b111 -
1%
#530000
0%
#535000
b10000 G
b1010000000000 ?
b10100000111 5
b11111010000 +
b11111010000 3
b1111101000 $
b1111101000 >
b100011110 <
b101000001111000 4
b1111 C
1!
b1000 -
b101110 E
1%
#540000
0%
#545000
b10000 G
b1011001000000 ?
b1111101000 +
b1111101000 3
b11111010000 $
b11111010000 >
b101000000 <
b10100000111 =
b0 C
b101000001111000 4
b101000001111000 B
1!
b101111 E
b1001 -
1%
#550000
0%
#555000
b10000 G
b1011111101000 ?
b10100111100 5
b11111010000 +
b11111010000 3
b1111101000 $
b1111101000 >
b101100100 <
b101001111001010 4
b1 C
1!
b1010 -
b110000 E
1%
#560000
0%
#565000
b10000 G
b1100110111110 ?
b1111101000 +
b1111101000 3
b11111010000 $
b11111010000 >
b101111110 <
b10100111100 =
b10 C
b101001111001010 4
b101001111001010 B
1!
b110001 E
b1011 -
1%
#570000
0%
#575000
b10000 G
b1101011111100 ?
b10101110001 5
b11111010000 +
b11111010000 3
b1111101000 $
b1111101000 >
b110011011 <
b101011100011100 4
b11 C
1!
b1100 -
b110010 E
1%
#580000
0%
#585000
b10000 G
b1110001101000 ?
b1111101000 +
b1111101000 3
b11111010000 $
b11111010000 >
b110101111 <
b10101110001 =
b100 C
b101011100011100 4
b101011100011100 B
1!
b110011 E
b1101 -
1%
#590000
0%
#595000
b10000 G
b1110100111100 ?
b10110100110 5
b11111010000 +
b11111010000 3
b1111101000 $
b1111101000 >
b111000110 <
b101101001101110 4
b101 C
1!
b1110 -
b110100 E
1%
#600000
0%
#605000
b10000 G
b1111000111110 ?
b1111101000 +
b1111101000 3
b11111010000 $
b11111010000 >
b111010011 <
b10110100110 =
b110 C
b101101001101110 4
b101101001101110 B
1!
b110101 E
b1111 -
1%
#610000
0%
#615000
b10000 G
b1111010101010 ?
b10111011100 5
b11111010000 +
b11111010000 3
b1111101000 $
b1111101000 >
b111100011 <
b101110111000000 4
b111 C
1!
b10000 -
b110110 E
1%
#620000
0%
#625000
b10000 G
b1111101000000 ?
b1111101000 +
b1111101000 3
b11111010000 $
b11111010000 >
b111101010 <
b10111011100 =
b1000 C
b101110111000000 4
b101110111000000 B
1!
b110111 E
b10001 -
1%
#630000
0%
#635000
b11111010000 +
b11111010000 3
b1111101000 $
b1111101000 >
b111110100 <
b101110111000000 4
b1001 C
1!
b10010 -
b111000 E
1%
#640000
0%
#645000
b1111101000 +
b1111101000 3
b11111010000 $
b11111010000 >
b101110111000000 4
b1010 C
1!
b111001 E
b10011 -
1%
#650000
0%
#655000
b11111010000 +
b11111010000 3
b1111101000 $
b1111101000 >
b101110111000000 4
b1011 C
1!
b10100 -
b111010 E
1%
#660000
0%
#665000
b10000 G
b1111101000000 ?
b11000011010 5
0,
b11111010000 $
b11111010000 >
b110000110101000 4
b1100 C
1!
b111011 E
1%
#670000
0%
#675000
0!
b111100 E
1%
