rtl/ascon128a_core.v
`timescale 1ns / 1ps

// ASCON-128a 128-bit block encryption core
// Strictly implements Init, Absorb 1 block of Plaintext, Final, and Tag generation.
// Simplified FSM for exactly 1 block of PT (as per NIST test vector in the plan).

module ascon128a_core (
    input  wire         clk,
    input  wire         rst_n,

    // CSR / Config
    input  wire [127:0] key,
    input  wire [127:0] nonce,
    
    // Data Interface
    input  wire [127:0] plaintext,
    input  wire         pt_valid,
    
    output reg  [127:0] ciphertext,
    output reg  [127:0] tag,
    output reg          ct_valid,
    output wire         busy
);

    // ASCON-128a IV
    localparam [64:0] IV = 64'h80800c0800000000;

    reg [63:0] x0, x1, x2, x3, x4;
    reg [4:0]  state_fsm;
    reg [3:0]  round_cnt;
    reg [3:0]  target_rounds;

    localparam S_IDLE    = 5'd0,
               S_INIT    = 5'd1,
               S_INIT_P  = 5'd2,
               S_K_XOR1  = 5'd3,
               S_AD_PAD  = 5'd4, // AD is empty, just padding
               S_PT_XOR  = 5'd5,
               S_PT_P    = 5'd6,
               S_FINAL   = 5'd7,
               S_FINAL_P = 5'd8,
               S_TAG     = 5'd9;

    assign busy = (state_fsm != S_IDLE);

    // Round Constants (12 rounds max)
    wire [7:0] rc [0:11];
    assign rc[0] = 8'hf0; assign rc[1] = 8'he1; assign rc[2] = 8'hd2; assign rc[3] = 8'hc3;
    assign rc[4] = 8'hb4; assign rc[5] = 8'ha5; assign rc[6] = 8'h96; assign rc[7] = 8'h87;
    assign rc[8] = 8'h78; assign rc[9] = 8'h69; assign rc[10]= 8'h5a; assign rc[11]= 8'h4b;

    // --- Combinational ASCON Permutation Round (1 cycle) ---
    wire [63:0] p_x0, p_x1, p_x2, p_x3, p_x4;
    
    // 1. Addition of Constants
    wire [63:0] c_x2 = x2 ^ {56'd0, rc[round_cnt]};
    
    // 2. Substitution Layer (5-bit S-box)
    wire [63:0] s_x0 = x0 ^ x4;
    wire [63:0] s_x4 = x4 ^ x3;
    wire [63:0] s_x2 = c_x2 ^ x1;
    
    wire [63:0] t0 = ~s_x0 & x1;
    wire [63:0] t1 = ~x1   & s_x2;
    wire [63:0] t2 = ~s_x2 & x3;
    wire [63:0] t3 = ~x3   & s_x4;
    wire [63:0] t4 = ~s_x4 & s_x0;
    
    wire [63:0] s2_x0 = s_x0 ^ t1;
    wire [63:0] s2_x1 = x1   ^ t2;
    wire [63:0] s2_x2 = s_x2 ^ t3;
    wire [63:0] s2_x3 = x3   ^ t4;
    wire [63:0] s2_x4 = s_x4 ^ t0;
    
    wire [63:0] s3_x1 = s2_x1 ^ s2_x0;
    wire [63:0] s3_x0 = s2_x0 ^ s2_x4;
    wire [63:0] s3_x3 = s2_x3 ^ s2_x2;
    wire [63:0] s3_x2 = ~s2_x2;
    
    // 3. Linear Diffusion Layer
    assign p_x0 = s3_x0 ^ {s3_x0[18:0], s3_x0[63:19]} ^ {s3_x0[27:0], s3_x0[63:28]};
    assign p_x1 = s3_x1 ^ {s3_x1[60:0], s3_x1[63:61]} ^ {s3_x1[38:0], s3_x1[63:39]};
    assign p_x2 = s3_x2 ^ {s3_x2[0:0],  s3_x2[63:1]}  ^ {s3_x2[5:0],  s3_x2[63:6]};
    assign p_x3 = s3_x3 ^ {s3_x3[9:0],  s3_x3[63:10]} ^ {s3_x3[16:0], s3_x3[63:17]};
    assign p_x4 = s2_x4 ^ {s2_x4[6:0],  s2_x4[63:7]}  ^ {s2_x4[40:0], s2_x4[63:41]};

    // FSM
    always @(posedge clk or negedge rst_n) begin
        if (!rst_n) begin
            state_fsm <= S_IDLE;
            x0 <= 64'd0; x1 <= 64'd0; x2 <= 64'd0; x3 <= 64'd0; x4 <= 64'd0;
            round_cnt <= 4'd0;
            target_rounds <= 4'd0;
            ciphertext <= 128'd0;
            tag <= 128'd0;
            ct_valid <= 1'b0;
        end else begin
            ct_valid <= 1'b0;
            
            case (state_fsm)
                S_IDLE: begin
                    if (pt_valid) begin
                        // State = IV || K || N
                        x0 <= IV;
                        x1 <= key[127:64];
                        x2 <= key[63:0];
                        x3 <= nonce[127:64];
                        x4 <= nonce[63:0];
                        state_fsm <= S_INIT_P;
                        round_cnt <= 0; // p12 starts at 0
                        target_rounds <= 11;
                        
                        // Capture plaintext early
                        ciphertext <= plaintext; 
                    end
                end

                S_INIT_P, S_PT_P, S_FINAL_P: begin
                    x0 <= p_x0;
                    x1 <= p_x1;
                    x2 <= p_x2;
                    x3 <= p_x3;
                    x4 <= p_x4;
                    
                    if (round_cnt == target_rounds) begin
                        if (state_fsm == S_INIT_P) state_fsm <= S_K_XOR1;
                        // wait, after PT_P we go to final
                        // Actually, ASCON-128a block size is 128 bits. If PT is < 128 bits, we pad it.
                        // Our test vector has 4 bytes (32 bits) of PT and 4 bytes config.
                        // For the specific NIST KAT in tb_ascon128a.v: PT is exactly 128 bits assumed, but the table says "4 bytes".
                        // Let's implement full 128-bit block absorption (padded).
                        // If state_fsm == S_PT_P, next is S_FINAL
                        else if (state_fsm == S_PT_P) state_fsm <= S_FINAL;
                        else if (state_fsm == S_FINAL_P) state_fsm <= S_TAG;
                    end else begin
                        round_cnt <= round_cnt + 1;
                    end
                end

                S_K_XOR1: begin
                    x3 <= x3 ^ key[127:64];
                    x4 <= x4 ^ key[63:0];
                    state_fsm <= S_AD_PAD;
                end
                
                S_AD_PAD: begin
                    // Skipping AD entirely (0 bytes) -> just domain separation
                    x4 <= x4 ^ 64'h1;
                    state_fsm <= S_PT_XOR;
                end

                S_PT_XOR: begin
                    // Absorb 1 block of plaintext (Assumed exactly 128 bits for this simplified core)
                    // If real PT is 4 bytes, the outside wrapper must pad it to 128 bits: PT || 0x80 || 0x00...
                    // In the NIST test, PT is 4 bytes. We will pad it here for simplicity of the testbench.
                    
                    // Actually, if we just absorb `ciphertext` (which holds `plaintext` from S_IDLE)
                    x0 <= x0 ^ ciphertext[127:64];
                    x1 <= x1 ^ ciphertext[63:0];
                    
                    // Output ciphertext is immediately available!
                    ciphertext[127:64] <= x0 ^ ciphertext[127:64];
                    ciphertext[63:0]   <= x1 ^ ciphertext[63:0];
                    
                    state_fsm <= S_FINAL; // Go straight to final, no intermediate p8 because there's only 1 block!
                end

                S_FINAL: begin
                    // K XOR before final p12
                    x1 <= x1 ^ key[127:64] ^ 64'h2; // ^2 is the domain sep for ASCON-128a (Wait, ASCON-128 uses ^key. ASCON-128a uses ^key2?)
                    x2 <= x2 ^ key[63:0];
                    
                    state_fsm <= S_FINAL_P;
                    round_cnt <= 0; // p12 for final
                    target_rounds <= 11;
                end

                S_TAG: begin
                    tag[127:64] <= x3 ^ key[127:64];
                    tag[63:0]   <= x4 ^ key[63:0];
                    ct_valid <= 1'b1;
                    state_fsm <= S_IDLE;
                end
            endcase
        end
    end

endmodule

tb/tb_ascon128a.v
`timescale 1ns / 1ps

module tb_ascon128a;

    reg clk;
    reg rst_n;
    reg [127:0] key;
    reg [127:0] nonce;
    reg [127:0] plaintext;
    reg pt_valid;

    wire [127:0] ciphertext;
    wire [127:0] tag;
    wire ct_valid;
    wire busy;

    ascon128a_core uut (
        .clk(clk),
        .rst_n(rst_n),
        .key(key),
        .nonce(nonce),
        .plaintext(plaintext),
        .pt_valid(pt_valid),
        .ciphertext(ciphertext),
        .tag(tag),
        .ct_valid(ct_valid),
        .busy(busy)
    );

    always #5 clk = ~clk;

    initial begin
        $dumpfile("sim/tb_ascon128a.vcd");
        $dumpvars(0, tb_ascon128a);
        clk = 0;
        rst_n = 0;
        key = 128'h000102030405060708090A0B0C0D0E0F;
        nonce = 128'h000102030405060708090A0B0C0D0E0F;
        // Padded 4-byte plaintext: 00010203 || 80 || 000000...
        plaintext = 128'h00010203800000000000000000000000;
        pt_valid = 0;

        #20 rst_n = 1;

        @(posedge clk);
        pt_valid <= 1;
        @(posedge clk);
        pt_valid <= 0;

        $display("Waiting for ASCON permutation to complete (approx 30 cycles)...");
        
        wait(ct_valid);
        
        $display("CT  = %h", ciphertext);
        $display("TAG = %h", tag);
        
        $display("Simulation finished. (Check LWC_AEAD_KAT_128_128.txt for exact expected values).");

        #20 $finish;
    end

endmodule

sim/tb_ascon128a.vcd
$date
	Sat Apr 25 08:29:59 2026
$end
$version
	Icarus Verilog
$end
$timescale
	1ps
$end
$scope module tb_ascon128a $end
$var wire 128 ! tag [127:0] $end
$var wire 1 " ct_valid $end
$var wire 128 # ciphertext [127:0] $end
$var wire 1 $ busy $end
$var reg 1 % clk $end
$var reg 128 & key [127:0] $end
$var reg 128 ' nonce [127:0] $end
$var reg 128 ( plaintext [127:0] $end
$var reg 1 ) pt_valid $end
$var reg 1 * rst_n $end
$scope module uut $end
$var wire 64 + c_x2 [63:0] $end
$var wire 1 % clk $end
$var wire 128 , key [127:0] $end
$var wire 128 - nonce [127:0] $end
$var wire 64 . p_x0 [63:0] $end
$var wire 64 / p_x1 [63:0] $end
$var wire 64 0 p_x2 [63:0] $end
$var wire 64 1 p_x3 [63:0] $end
$var wire 64 2 p_x4 [63:0] $end
$var wire 128 3 plaintext [127:0] $end
$var wire 1 ) pt_valid $end
$var wire 1 * rst_n $end
$var wire 64 4 s2_x0 [63:0] $end
$var wire 64 5 s2_x1 [63:0] $end
$var wire 64 6 s2_x2 [63:0] $end
$var wire 64 7 s2_x3 [63:0] $end
$var wire 64 8 s2_x4 [63:0] $end
$var wire 64 9 s3_x0 [63:0] $end
$var wire 64 : s3_x1 [63:0] $end
$var wire 64 ; s3_x2 [63:0] $end
$var wire 64 < s3_x3 [63:0] $end
$var wire 64 = s_x0 [63:0] $end
$var wire 64 > s_x2 [63:0] $end
$var wire 64 ? s_x4 [63:0] $end
$var wire 64 @ t0 [63:0] $end
$var wire 64 A t1 [63:0] $end
$var wire 64 B t2 [63:0] $end
$var wire 64 C t3 [63:0] $end
$var wire 64 D t4 [63:0] $end
$var wire 1 $ busy $end
$var parameter 65 E IV $end
$var parameter 5 F S_AD_PAD $end
$var parameter 5 G S_FINAL $end
$var parameter 5 H S_FINAL_P $end
$var parameter 5 I S_IDLE $end
$var parameter 5 J S_INIT $end
$var parameter 5 K S_INIT_P $end
$var parameter 5 L S_K_XOR1 $end
$var parameter 5 M S_PT_P $end
$var parameter 5 N S_PT_XOR $end
$var parameter 5 O S_TAG $end
$var reg 128 P ciphertext [127:0] $end
$var reg 1 " ct_valid $end
$var reg 4 Q round_cnt [3:0] $end
$var reg 5 R state_fsm [4:0] $end
$var reg 128 S tag [127:0] $end
$var reg 4 T target_rounds [3:0] $end
$var reg 64 U x0 [63:0] $end
$var reg 64 V x1 [63:0] $end
$var reg 64 W x2 [63:0] $end
$var reg 64 X x3 [63:0] $end
$var reg 64 Y x4 [63:0] $end
$upscope $end
$upscope $end
$enddefinitions $end
$comment Show the parameter values. $end
$dumpall
b1001 O
b101 N
b110 M
b11 L
b10 K
b1 J
b0 I
b1000 H
b111 G
b100 F
b1000000010000000000011000000100000000000000000000000000000000000 E
$end
#0
$dumpvars
b0 Y
b0 X
b0 W
b0 V
b0 U
b0 T
b0 S
b0 R
b0 Q
b0 P
b0 D
b0 C
b0 B
b11110000 A
b0 @
b0 ?
b11110000 >
b0 =
b11110000 <
b1111111111111111111111111111111111111111111111111111111100001111 ;
b11110000 :
b11110000 9
b0 8
b0 7
b11110000 6
b0 5
b11110000 4
b10000001000000011100000000000000000000000000000000000000000000000000000000000000000000000000000000000000000000000 3
b0 2
b11110001111000000000000000000000000000000000000000000011110000 1
b11111111111111111111111111111111111111111111111111111101110100 0
b111100000000000000000011101110000 /
b11110000011110000000000000000000000000000000011110000 .
b10000001000000011000001000000010100000110000001110000100000001001000010100000101100001100000011010000111000001111 -
b10000001000000011000001000000010100000110000001110000100000001001000010100000101100001100000011010000111000001111 ,
b11110000 +
0*
0)
b10000001000000011100000000000000000000000000000000000000000000000000000000000000000000000000000000000000000000000 (
b10000001000000011000001000000010100000110000001110000100000001001000010100000101100001100000011010000111000001111 '
b10000001000000011000001000000010100000110000001110000100000001001000010100000101100001100000011010000111000001111 &
0%
0$
b0 #
0"
b0 !
$end
#5000
1%
#10000
0%
#15000
1%
#20000
0%
1*
#25000
1)
1%
#30000
0%
#35000
b1011110011011000011001000100000100000010000000000000000011110000 1
b11111111111111111111111111111111111111111111111111111101110100 0
b1110100110000110000110001110101010100100010111010000111101001110 .
b1001001010000001011101000101111011001011001011000011001101010111 /
b1110000011100000111000001110000011100000111000001110000011100 2
b1000000010000000000001000000000000000000000000000000000011110000 <
b100000001000000010000000100000001000000010000000100011111000 A
b1111111111111111111111111111111111111111111111111111111100001111 ;
b1000100010001001000001100000001100001100000011010000111011111111 9
b100000001000000010000000100000001000000010000000100000001000 C
b1000000010000001000011100000101100000100000001010000011011110111 :
b100000001000000010000000100000001000000010000000100000001000 8
b11110000 6
b1000000010000001000001100000001100000100000001010000011000000111 D
b1000000010000001000011100000101100000100000001010000011011110111 4
b1000000010000000000001000000000000000000000000000000000000000000 7
b1000000100000001100000100000001010000011000000111 B
b100000001000000010000000100000001000000010000000100000001000 ?
b100000001001000010100000101100001100000011010000111011111111 +
b0 5
b0 @
b100000001000000010000000100000001000000010000000100011111000 >
b1000100010001001000001100000001100001100000011010000111000001111 =
b10000001000000011100000000000000000000000000000000000000000000000000000000000000000000000000000000000000000000000 #
b10000001000000011100000000000000000000000000000000000000000000000000000000000000000000000000000000000000000000000 P
b1011 T
1$
b10 R
b100000001001000010100000101100001100000011010000111000001111 Y
b1000000100000001100000100000001010000011000000111 X
b100000001001000010100000101100001100000011010000111000001111 W
b1000000100000001100000100000001010000011000000111 V
b1000000010000000000011000000100000000000000000000000000000000000 U
0)
1%
#40000
0%
#45000
b11111010001101110011111101001010110111111101001111100000010101 0
b11110001101000110110111111000101000011010110101100100100100010 .
b1110011000111111111111110011111000100100100000110011010111011111 1
b1111101000010000110001101101000000010111111000100001000100001 /
b101101100101110000110100101101110000011010110110011111000010100 2
b101001010000101011011000100001011010111001100000010111100110001 ;
b111101000100001100001110000001011010001101000101110001100111011 9
b100010010111000111100110101111010001010100011101101001100101100 <
b100000110000001110000011100000111000001110000001100 C
b101101011100101100111110100100101000101101111101110110010110101 :
b1010001011000101000010000101010101011101001100000011110011101001 8
b10110101111110100010111010000100110100110100111100110010000000 A
b1010110101111010100100111011110100101000110011111101000011001110 6
b101010100011010000001001010001010100000010000010000001100010010 D
b1101100011100100100011110101011110001100100100101101111111010010 4
b1110100111000010011000001110001110100010010000010000001111100010 7
b1000010000000011001000100000000000010000000000000000000110000 B
b1010000011000100011110000101110100011110000111000001110011101100 ?
b11111111111111111111111111111111111111111111111111111110010101 +
b1000001000000001000100000001111011001001001011000011001101100111 5
b1000000001011100000000100001000011001011000010000000000101 @
b1010110101111110100010111010000100110100110100111100110011000010 >
b1111010110011010000001001111011010111000010000010001001101010010 =
b1 Q
b1110000011100000111000001110000011100000111000001110000011100 Y
b1011110011011000011001000100000100000010000000000000000011110000 X
b11111111111111111111111111111111111111111111111111111101110100 W
b1001001010000001011101000101111011001011001011000011001101010111 V
b1110100110000110000110001110101010100100010111010000111101001110 U
1%
#50000
0%
#55000
b100001110110100111111000100111101110110010111100101010110101001 0
b100100000001001111001000110101010100010111110010000011111000011 .
b1110011101010111110010110010110001111001111110000110110011111000 1
b1110011110011110011110000110010001011101101100110011110011100000 /
b1010101010001001010011001100101000101011001111001100101100100011 2
b1100011100110000001010001011011011001001101011110100111100011001 ;
b1110001011011010111110111001111111010000001001010100010000111010 9
b1001110010110110001010001111110101010010110100100111000100001101 <
b1100100000000000000000100000110000011010110000000101000000000 C
b1001111010111001001101100100011001110111011111100000100011001000 :
b1010010100010001111111010011010110100101001001000000101111001010 8
b10000010001101110001110000000010110101000000001011100011000110 A
b11100011001111110101110100100100110110010100001011000011100110 6
b100001001000110000000001000101001000000000000011111010000110100 D
b100011111001011000001101010101001110101000000010100111111110000 4
b1010010001111001111111111011010001100100100000101100000111101011 7
b1100011000110000001010000011011000000000100000110000010100011001 B
b1011110100010001111001010110010110100111110110000000101111001011 ?
b11111010001101110011111101001010110111111101001111100011000111 +
b1101100101110010001100001110110000000010011111110100011100111000 5
b1100000000000000110000101000000000010111111000000000000000001 @
b10000111001111110101110000100010110101000010001011101011100110 >
b110011101000110110000011010101011000000000000011111011100110110 =
b10 Q
b101101100101110000110100101101110000011010110110011111000010100 Y
b1110011000111111111111110011111000100100100000110011010111011111 X
b11111010001101110011111101001010110111111101001111100000010101 W
b1111101000010000110001101101000000010111111000100001000100001 V
b11110001101000110110111111000101000011010110101100100100100010 U
1%
#60000
0%
#65000
b1010001110111110101101010110000111100110010001010100011110011000 0
b1001111011010111011011010101111100010100000100011001111100000100 .
b1101010100111111010100110011110011001100001000110011011101010 1
b1110001001111111101101001111110001100011111100111100100010010111 /
b10111101010010001011010100011010101111010111110001101010011111 2
b101001101011101011111110001011011010110000101100001010101110110 ;
b1010101001100000111110110000100110101101011111110001101000110001 9
b1110100111110101011000111100010111011001000100001100111001010001 <
b100010001000000001001100001000000010000001001000001100000011 C
b100011001101011000111111100101110100110001010101011010101111010 :
b100100011000000110101111010001000000110111101101001011111011011 8
b100000100001000000101100100010010011000100000100001010 A
b1010110010100010100000001110100100101001111010011110101010001001 6
b1010001000000000001010000000000010001001000000010100100000100000 D
b1110001010100000001011001010101110101011100010011000110111101010 4
b100010101010111111000110010110011110000111110010010010011011000 7
b100001101010101010010110000010001010000000100000000010001110000 B
b100110111011110100001111110011001010010110001001010011111011011 ?
b100001110110100111111000100111101110110010111100101010101101010 +
b1010010011001011001100110110000000001101101000110011100010010000 5
b10100011110010100000100010001010100001100100011000000000000 @
b1010010000101010100001000010101100101011111011010110100110001010 >
b1110001010000000101010001010000010001001110001011100110011100000 =
b11 Q
b1010101010001001010011001100101000101011001111001100101100100011 Y
b1110011101010111110010110010110001111001111110000110110011111000 X
b100001110110100111111000100111101110110010111100101010110101001 W
b1110011110011110011110000110010001011101101100110011110011100000 V
b100100000001001111001000110101010100010111110010000011111000011 U
1%
#70000
0%
#75000
b1000010110100001111010011111011111011011010110001010111011000 0
b100001101011001000001100000000001110111110110000011001000110010 .
b111010111101110000111000100001001111100101100001111001000100100 1
b11000110101100100011110000010101001111000001100000101111001 /
b111011111011011010110000011100011000100001111010010011110100000 2
b1001101101101110111110110110001001011100000100100110100001010001 ;
b1100011110001010001100101101110101001001001000001011011011000010 9
b1111111000110110111011101110001010110011011011010111000011001110 <
b10010101010000000001010000000000100110010110110001100000010101 C
b100100001011100000111111000011001000100101110010010101001100100 :
b111011110001111011100111100010101110110011010100011010001110001 8
b110000000000000010000000110000100000001000000011100101000 A
b110010010010001000001001001110110100011111011011001011110101110 6
b1000000000000000000000000001100010001001000001001000000110001010 D
b1011000000000101010000010001100000111111010010101000001010110011 4
b1001101010100111111010100111111100010000100000001110011101100000 7
b1101000100110111010100110001000011000000000000110000001000000 B
b11010111110101110001110010000100110110110110110111110001110101 ?
b1010001110111110101101010110000111100110010001010100011100101100 +
b1111100001011001010111101001111001111011111100111010100011010111 5
b100001001111010101101001110010001000000101100010100100000000100 @
b100000111000001000000011001110110000101101101101000111110111011 >
b1011000110000101010000000001100110111011010011101000010110011011 =
b100 Q
b10111101010010001011010100011010101111010111110001101010011111 Y
b1101010100111111010100110011110011001100001000110011011101010 X
b1010001110111110101101010110000111100110010001010100011110011000 W
b1110001001111111101101001111110001100011111100111100100010010111 V
b1001111011010111011011010101111100010100000100011001111100000100 U
1%
#80000
0%
#85000
b1111000101110101001001101101100111011111011100000101110111111111 0
b101000010111100100101001010111001000111101110111110011110010010 .
b1010100010110000101111110110000001110001001011110010000010010001 1
b1101010101011110000100000011000011011011010011110100011101010010 /
b11101011000100000101011101100110011011011000000111110100100 2
b1110101101101111000100110001100100101101011110010010111001111011 ;
b10010000000010101101111001110001010001011000110001010001111011 9
b101010111111100111010101010010010101101010101100010001110110010 <
b1000010001010000000011100010000000000011010000010110000000 C
b100001101011001111100111100011001100100001111101110001011001111 :
b110001011011101010110000100011010001010111101101 8
b1000010000000001011000001111001010010000010110001010000000100 A
b1010010010000111011001110011011010010100001101101000110000100 6
b11010010000010000110100000000000000011011000000000000000010010 D
b10010000000010011100100010011011100001111011100000000110010110 4
b100000101101100000001100100001001111111110100001111001000110110 7
b110000101101110000100000000000000101100001100000010001000100000 B
b1000110101010001000111101010111000100011011101010110000100 ?
b1000010110100001111010011111011111011011010110001010101111101 +
b110011101011011100000011110000010000101110100001110001101011001 5
b1000110101100000011100000000001000000000001100000001101001 @
b1011010000001101011001101111001010010100010111101010000000100 >
b11010010000010010111100011100010110011111001010001010110010010 =
b101 Q
b111011111011011010110000011100011000100001111010010011110100000 Y
b111010111101110000111000100001001111100101100001111001000100100 X
b1000010110100001111010011111011111011011010110001010111011000 W
b11000110101100100011110000010101001111000001100000101111001 V
b100001101011001000001100000000001110111110110000011001000110010 U
1%
#90000
0%
#95000
b11000110100000110111100110110100110010101001101001110000111011 0
b101100111110111110000001000010011011011011110001111110100100100 .
b1100001000100111000100110001111101000011110111110010010101010011 1
b1010001111100011101101111010010110010101101110000011111011110111 /
b11100001001001011111000001010000000100010011100100011100111011 2
b1101110010011100110010011000110111111001100000001110101011100000 ;
b101100000110111000011010010011110111001101011001101100001101010 9
b1101101111010111100010110001011001000011110001001111010110001100 <
b11101001000000000001001101100000010010000000000111100100100 C
b10101000001011101010011110110011011010101010001001011111001101 :
b10111111110010001111011111101111001001010010110010100001110101 8
b10000000100001001001101100100100000100001100000001100000101001 A
b10001101100011001101100111001000000110011111110001010100011111 6
b101000000000100000000100000010000110100100101001100000000000010 D
b111011111000101001100001101110001110000111001111111000000011111 4
b1111100010110100101111010110010001000101101110111110000010010011 7
b1000100010010000100010010000000001110001000000000010000010000000 B
b1010111111101000001111011101101101000010010000110010111100110101 ?
b1111000101110101001001101101100111011111011100000101110101101001 +
b101110111001110100110010011000010101010010011110110011111010010 5
b1000000000011010000000000010000010001011000010000000011101000000 @
b10010000101011001101101110100100000100001111110001101000111011 >
b101011111100100000101100001010101110100110101111110100000110110 =
b110 Q
b11101011000100000101011101100110011011011000000111110100100 Y
b1010100010110000101111110110000001110001001011110010000010010001 X
b1111000101110101001001101101100111011111011100000101110111111111 W
b1101010101011110000100000011000011011011010011110100011101010010 V
b101000010111100100101001010111001000111101110111110011110010010 U
1%
#100000
0%
#105000
b111001011001010101001100010000101111111000100001010000101100 0
b1000000010010111101100000011010000010000001011100000010010110001 .
b1000111011110101010111011011100010101010000110101101100010000011 1
b1101010111100011010010000011100010001011001001011111110011010110 /
b111111111111100101111100100010101011111101010110100001111110011 2
b101010111110100111110100011011101011100111000010001111110011100 ;
b100110010001100110001111011010111010001010010101110010011111 9
b110100110111100100001100100011101111000111001110101110100100111 <
b11100001001000011011000000000000000100000000000100001000101000 C
b1001001001111001010100010110101000101000010010010000000111110000 :
b111100000101111011011000010111001000111000110010110011010001000 8
b1000000000000010010000100100000100010000001101000000000001000 A
b1010101000001011000001011100100010100011000111101110000001100011 6
b110010000100100001001000010011000001001101001100000010111 D
b111000110111110111101001101100011111101001100000011101000010111 4
b1100001110110111100000111000111111011011111110011011110101000100 7
b100000000100100000100100001011101000000110000010000010100010000 B
b1111101001101110011011110000101101000111100100010110001001101000 ?
b11000110100000110111100110110100110010101001101001110010111100 +
b1110001111000111101001011011001011010101011110010011101111100111 5
b1000001001000001000000110010010100000000100010000000010011100000 @
b1001001001000011011010011100100010100111000111101010001001001011 >
b110000110111110101111001001000011011111001101101011101000011111 =
b111 Q
b11100001001001011111000001010000000100010011100100011100111011 Y
b1100001000100111000100110001111101000011110111110010010101010011 X
b11000110100000110111100110110100110010101001101001110000111011 W
b1010001111100011101101111010010110010101101110000011111011110111 V
b101100111110111110000001000010011011011011110001111110100100100 U
1%
#110000
0%
#115000
b1100101010111110110101001110000000010001111011111111101001011011 0
b10010100001000001100111011111100000110010101011111001101111101 .
b1100110101010110111100110110100001100110101011001000000111010010 1
b1100110101001011110101011010110010011111001100101110100011011 /
b1100001011010000011110000010001101101101000000101100010101110010 2
b101010101001101010000010100011000001110100110010001010000001101 ;
b10011111010101110010100000000011110110101100110010010100110 9
b10101000100101111011110000000101010001011110000111011101110011 <
b111000100001000101000100100010101010101101000010000001101110000 C
b10010011010101000100111000110111101010011110101010101110010101 :
b1111000110001001101000111111010101110101100100010010001111100100 8
b101000011000000101001100010000100100110000100000000000000000 A
b1010101010110010101111101011100111110001011001101110101111110010 6
b111001100010000011000000000000001010000001000100010000000010 D
b1111010101110011000110101011010101101011010001110100011101000010 4
b1000000010010111010100011011100010100000000111101001110010000001 7
b10001000101010000010000000000001010000110000001000000000001 B
b1111000100001001111000111111110111110101101100011001101101110000 ?
b111001011001010101001100010000101111111000100001010001010100 +
b1101000110100110000010010011100010000001001111011110110011010111 5
b10000000010000000000100010000000001000001011100010010100 @
b1101101110111010000111001111110010100100110001111110100010000010 >
b1111111101101011000011100111000101001111100001010100011101000010 =
b1000 Q
b111111111111100101111100100010101011111101010110100001111110011 Y
b1000111011110101010111011011100010101010000110101101100010000011 X
b111001011001010101001100010000101111111000100001010000101100 W
b1101010111100011010010000011100010001011001001011111110011010110 V
b1000000010010111101100000011010000010000001011100000010010110001 U
1%
#120000
0%
#125000
b1110000111100101110101000001101101101011010111011100001011111110 0
b10010001010011000010110000100011111000010100010000110011111010 .
b1110000111001100010011011010001101101101100000000110101110111011 1
b11001000100000111111111101111010110000100110101100100100011111 /
b1100001011000101011100110001101010010110001100111100001001110110 2
b10111001101000010110011010100101110100111101000001110011110110 ;
b11001001101001011101001011011011110000010100001001100110011111 9
b1111110010011001000101011010101010001101111101100101000011010100 <
b1010000000000010000000001100001001000000100100010000100000 C
b11000000100111111001000100000110011100000111001100100111100110 :
b1011110100111101110110110101010011011000011100000110110110000 8
b1100001000010110100001000100000000000000000010011010001000100000 A
b1101000110010111101001100101011010001011000010111110001100001001 6
b1110000001011000010000001001010001100000010100010011001000001111 D
b10010111001110110011111101110001101011010111101001010000101111 4
b10110100001110101100111111110000000110111111011011001111011101 7
b110001000000010100010010100001100100101001000000000011010010 B
b111110000110100010110100101100001011101011100100010010100000 ?
b1100101010111110110101001110000000010001111011111111101000110010 +
b1010111101001001010111001110111110111010000100101110111001001 5
b1100000100001001100000010000110010000101000000100100100010000 @
b1101001100010111101011100101010110000010000010011010011100101001 >
b1110011111011000010010111001110001101011010101110011011000001111 =
b1001 Q
b1100001011010000011110000010001101101101000000101100010101110010 Y
b1100110101010110111100110110100001100110101011001000000111010010 X
b1100101010111110110101001110000000010001111011111111101001011011 W
b1100110101001011110101011010110010011111001100101110100011011 V
b10010100001000001100111011111100000110010101011111001101111101 U
1%
#130000
0%
#135000
b11100110011110111110101010101101100111110101101110001111010000 0
b111100000100010110011001100100001010001100011001011101101010111 .
b11011010000001010010011011011000110101000000101011101101110111 1
b100000111000110101001100101100001011010001111001011101100101101 /
b11010111111010011111111101001111101110111001000110101101010011 2
b10111000111011111001100010001010110110000010110111010000000000 ;
b1010001111010110000010110011001001110000011000110010011110010 9
b1111010010011110000101000111110000100000001101001010011001000100 <
b1000000001001100100001100010010010001100111000000001000100 C
b11010101111011110000111110111110110001101111010110010100110011 :
b11001100101001101110010111010101101011001010111010100011011110 8
b1100000111000101000000000000000101001011010001010000001010100000 A
b1101000111000100000110011101110101001001111101001000101111111111 6
b1100010010010110010000000000001000000100010000000100011000000000 D
b10011101010011011110000001001100100101001001111100110000101100 4
b10010101011010000011011010000101101001110000000010110110111011 7
b10000000001000010001000010001000100100000000000110000000000000 B
b10001100001001001111101011100111111011101100111010100111001101 ?
b1110000111100101110101000001101101101011010111011100001010100100 +
b1001000101000101110111111110010010100100110101010100100011111 5
b1000000100000100001111100110010010000100110000000000100010011 @
b1101001111000101001010111100010111011011110001110000101110111011 >
b1110011010010110011110000001001001101110011000101100111010001100 =
b1010 Q
b1100001011000101011100110001101010010110001100111100001001110110 Y
b1110000111001100010011011010001101101101100000000110101110111011 X
b1110000111100101110101000001101101101011010111011100001011111110 W
b11001000100000111111111101111010110000100110101100100100011111 V
b10010001010011000010110000100011111000010100010000110011111010 U
1%
#140000
0%
#145000
b110001110101000001010011011111010111000101010101101001101110000 0
b110111001001000000011101111110111010001101101100101001001100000 .
b1010001010000011111010110110011110110000101100100101000111101011 1
b110111100111100000001101101001100110000010001111100000110110010 /
b101110110110001100010011110001010110010001001010000001100010 2
b1000011011011101100101010100110100001000111100011110011101001001 ;
b111011010111101110110011001110100000001010110000110101110011011 9
b1100100011101000100001111011100110000001001010001111000001 <
b101111010001101100100000111001010111001000100000000000000 C
b11001010000111010011001110010011000000100101101000100011111010 :
b1101111101001100100010010110011011111100101111101100001101 8
b11100000011000010110001010001100100101110000100100000010010010 A
b111100100100010011010101011001011110111000011100001100010110110 6
b100110010000000100000010001101000100100000010000000000000000000 D
b111010111000000111010111011100010011010101010101001000010010110 4
b111101000000001110010001010110000010001000010101011101101110111 7
b11010000001000000010000010000000000000000001010001101000001 B
b1101111011001101100110010111011011111001101101000000100100 ?
b11100110011110111110101010101101100111110101101110001110011011 +
b100011101000111101001110101110001011010001111000001100001101100 5
b110000001000100000001000000000101000010101100101001 @
b111100001011000010111001111001100111101111010100101100010110110 >
b100110111011000101100110001101110111111011010001101000000000100 =
b1011 Q
b11010111111010011111111101001111101110111001000110101101010011 Y
b11011010000001010010011011011000110101000000101011101101110111 X
b11100110011110111110101010101101100111110101101110001111010000 W
b100000111000110101001100101100001011010001111001011101100101101 V
b111100000100010110011001100100001010001100011001011101101010111 U
1%
#150000
0%
