rtl/dptc_encoder.v
`timescale 1ns / 1ps

module dptc_encoder (
    input  wire        clk,
    input  wire        rst_n,

    // CSR Interface
    input  wire        csr_en,
    input  wire        csr_force_reset,
    
    // Data Path Interface
    input  wire [15:0] sample_in,
    input  wire        valid_in,
    input  wire        ready_in,

    output reg  [15:0] delta_out,
    output reg  [4:0]  bit_width,
    output reg         is_absolute,
    output reg         valid_out,
    output wire        ready_out
);

    assign ready_out = !valid_out || ready_in;

    // Internal state
    reg [15:0] prev_sample;
    reg        sync_lost;

    wire signed [16:0] diff = $signed({1'b0, sample_in}) - $signed({1'b0, prev_sample});

    // Helper function to calculate bit width of a signed delta
    function [4:0] calc_width;
        input signed [16:0] d;
        begin
            if (d == 0) calc_width = 1;
            else if (d >= -1 && d <= 0) calc_width = 2; // -1, 0 handled by 2 bits. Wait, 0 is 1 bit. -1 is 2 bits (-1 = 2'b11).
            else if (d >= -2 && d <= 1) calc_width = 3; 
            else if (d >= -4 && d <= 3) calc_width = 4;
            else if (d >= -8 && d <= 7) calc_width = 5;
            else if (d >= -16 && d <= 15) calc_width = 6;
            else if (d >= -32 && d <= 31) calc_width = 7;
            else if (d >= -64 && d <= 63) calc_width = 8;
            else if (d >= -128 && d <= 127) calc_width = 9;
            else if (d >= -256 && d <= 255) calc_width = 10;
            else if (d >= -512 && d <= 511) calc_width = 11;
            else if (d >= -1024 && d <= 1023) calc_width = 12;
            else if (d >= -2048 && d <= 2047) calc_width = 13;
            else if (d >= -4096 && d <= 4095) calc_width = 14;
            else if (d >= -8192 && d <= 8191) calc_width = 15;
            else calc_width = 16;
        end
    endfunction

    always @(posedge clk or negedge rst_n) begin
        if (!rst_n) begin
            prev_sample <= 16'd0;
            sync_lost   <= 1'b1;
            delta_out   <= 16'd0;
            bit_width   <= 5'd0;
            is_absolute <= 1'b0;
            valid_out   <= 1'b0;
        end else begin
            if (csr_en && csr_force_reset) begin
                sync_lost <= 1'b1;
            end
            
            if (ready_out) begin
                valid_out <= valid_in;
                if (valid_in) begin
                    prev_sample <= sample_in;
                    
                    if (sync_lost) begin
                        // First sample is sent absolute
                        delta_out   <= sample_in;
                        bit_width   <= 5'd16;
                        is_absolute <= 1'b1;
                        sync_lost   <= 1'b0;
                    end else begin
                        // Compute delta and width
                        delta_out   <= diff[15:0];
                        bit_width   <= calc_width(diff);
                        is_absolute <= 1'b0;
                    end
                end
            end
        end
    end

endmodule

tb/tb_dptc_encoder.v
`timescale 1ns / 1ps

module tb_dptc_encoder;

    reg clk;
    reg rst_n;
    reg csr_en;
    reg csr_force_reset;
    reg [15:0] sample_in;
    reg valid_in;

    wire [15:0] delta_out;
    wire [4:0] bit_width;
    wire is_absolute;
    wire valid_out;

    dptc_encoder uut (
        .clk(clk),
        .rst_n(rst_n),
        .csr_en(csr_en),
        .csr_force_reset(csr_force_reset),
        .sample_in(sample_in),
        .valid_in(valid_in),
        .ready_in(1'b1),
        .delta_out(delta_out),
        .bit_width(bit_width),
        .is_absolute(is_absolute),
        .valid_out(valid_out),
        .ready_out()
    );

    always #5 clk = ~clk;

    initial begin
        $dumpfile("sim/tb_dptc_encoder.vcd");
        $dumpvars(0, tb_dptc_encoder);
        clk = 0;
        rst_n = 0;
        csr_en = 0;
        csr_force_reset = 0;
        sample_in = 0;
        valid_in = 0;

        #20 rst_n = 1;

        // Sample 1: Absolute
        @(posedge clk);
        sample_in <= 16'd1000;
        valid_in <= 1;
        @(posedge clk);
        valid_in <= 0;
        @(posedge clk);
        if (delta_out == 16'd1000 && is_absolute == 1'b1 && bit_width == 16) 
            $display("PASS: First sample is absolute");
        else 
            $display("FAIL: First sample not absolute");

        // Sample 2: Delta = +1 
        @(posedge clk);
        sample_in <= 16'd1001; 
        valid_in <= 1;
        @(posedge clk);
        valid_in <= 0;
        @(posedge clk);
        if (delta_out == 16'd1 && bit_width == 3 && is_absolute == 0) // diff=1 fits in 3 bits (sign + magnitude) -> Wait, 1 fits in 3 bits: 001. No wait, 1 fits in 3 bits [-2, 1] Wait, 1 fits in 3 bits. Let's check calc_width. 
            $display("PASS: Delta +1 width %d", bit_width);
        else 
            $display("FAIL: Delta +1 wrong, got %h w=%d", delta_out, bit_width);

        // Sample 3: Delta = -3
        @(posedge clk);
        sample_in <= 16'd998; 
        valid_in <= 1;
        @(posedge clk);
        valid_in <= 0;
        @(posedge clk);
        if (delta_out == 16'hFFFD && bit_width == 4 && is_absolute == 0) // diff=-3 fits in 4 bits [-4..3]
            $display("PASS: Delta -3 width 4 (val=%h)", delta_out);
        else 
            $display("FAIL: Delta -3 wrong, got %h w=%d", delta_out, bit_width);

        // Force reset
        @(posedge clk);
        csr_en <= 1;
        csr_force_reset <= 1;
        @(posedge clk);
        csr_en <= 0;
        csr_force_reset <= 0;
        
        // Sample 4: Absolute again
        @(posedge clk);
        sample_in <= 16'd500; 
        valid_in <= 1;
        @(posedge clk);
        valid_in <= 0;
        @(posedge clk);
        if (is_absolute == 1'b1 && delta_out == 16'd500)
            $display("PASS: Re-sync triggered absolute sample");
        else
            $display("FAIL: Re-sync failed");

        #20 $finish;
    end

endmodule

sim/tb_dptc_encoder.vcd
$date
	Sat Apr 25 09:32:09 2026
$end
$version
	Icarus Verilog
$end
$timescale
	1ps
$end
$scope module tb_dptc_encoder $end
$var wire 1 ! valid_out $end
$var wire 1 " is_absolute $end
$var wire 16 # delta_out [15:0] $end
$var wire 5 $ bit_width [4:0] $end
$var reg 1 % clk $end
$var reg 1 & csr_en $end
$var reg 1 ' csr_force_reset $end
$var reg 1 ( rst_n $end
$var reg 16 ) sample_in [15:0] $end
$var reg 1 * valid_in $end
$scope module uut $end
$var wire 1 % clk $end
$var wire 1 & csr_en $end
$var wire 1 ' csr_force_reset $end
$var wire 1 + ready_in $end
$var wire 1 , ready_out $end
$var wire 1 ( rst_n $end
$var wire 16 - sample_in [15:0] $end
$var wire 1 * valid_in $end
$var wire 17 . diff [16:0] $end
$var reg 5 / bit_width [4:0] $end
$var reg 16 0 delta_out [15:0] $end
$var reg 1 " is_absolute $end
$var reg 16 1 prev_sample [15:0] $end
$var reg 1 2 sync_lost $end
$var reg 1 ! valid_out $end
$scope function calc_width $end
$var reg 17 3 d [16:0] $end
$upscope $end
$upscope $end
$upscope $end
$enddefinitions $end
$comment Show the parameter values. $end
$dumpall
$end
#0
$dumpvars
bx 3
12
b0 1
b0 0
b0 /
b0 .
b0 -
1,
1+
0*
b0 )
0(
0'
0&
0%
b0 $
b0 #
0"
0!
$end
#5000
1%
#10000
0%
#15000
1%
#20000
0%
1(
#25000
1*
b1111101000 .
b1111101000 )
b1111101000 -
1%
#30000
0%
#35000
02
1"
b10000 $
b10000 /
b1111101000 #
b1111101000 0
b0 .
b1111101000 1
1!
0*
1%
#40000
0%
#45000
0!
1%
#50000
0%
#55000
1*
b1 .
b1111101001 )
b1111101001 -
1%
#60000
0%
#65000
0"
b11 $
b11 /
b1 #
b1 0
b0 .
b1111101001 1
1!
0*
b1 3
1%
#70000
0%
#75000
0!
1%
#80000
0%
#85000
1*
b11111111111111101 .
b1111100110 )
b1111100110 -
1%
#90000
0%
#95000
b100 $
b100 /
b1111111111111101 #
b1111111111111101 0
b0 .
b1111100110 1
1!
0*
b11111111111111101 3
1%
#100000
0%
#105000
0!
1%
#110000
0%
#115000
1'
1&
1%
#120000
0%
#125000
12
0'
0&
1%
#130000
0%
#135000
1*
b11111111000001110 .
b111110100 )
b111110100 -
1%
#140000
0%
#145000
02
1"
b10000 $
b10000 /
b111110100 #
b111110100 0
b0 .
b111110100 1
1!
0*
1%
#150000
0%
#155000
0!
1%
