rtl/fifo_sync.v
`timescale 1ns / 1ps

module fifo_sync #(
    parameter DATA_WIDTH = 8,
    parameter DEPTH_LOG2 = 11 // 2048 elements
)(
    input  wire                  clk,
    input  wire                  rst_n,
    
    // CSR Interface
    input  wire                  csr_en,
    input  wire                  csr_flush,
    input  wire                  csr_clear_overflow,
    input  wire [DEPTH_LOG2-1:0] csr_watermark,

    // Write Interface
    input  wire [DATA_WIDTH-1:0] wr_data,
    input  wire                  wr_en,
    
    // Read Interface
    output reg  [DATA_WIDTH-1:0] rd_data,
    input  wire                  rd_en,
    output reg                   rd_valid,   // Asserted 1 cycle after rd_en when data was available
    
    // Status Flags
    output wire                  full,
    output wire                  empty,
    output wire                  almost_full,
    output wire                  almost_empty,
    output reg                   overflow,
    output wire [DEPTH_LOG2:0]   level
);

    localparam DEPTH = 1 << DEPTH_LOG2;

    // Use a RAM block for storage (Vivado infers Block RAM easily from this pattern)
    reg [DATA_WIDTH-1:0] ram [0:DEPTH-1];
    
    reg [DEPTH_LOG2:0] count;
    reg [DEPTH_LOG2-1:0] wr_ptr;
    reg [DEPTH_LOG2-1:0] rd_ptr;

    wire [DEPTH_LOG2-1:0] active_watermark = (csr_watermark > 0) ? csr_watermark : (DEPTH - (DEPTH/4)); // Default 75%

    assign full = (count == DEPTH);
    assign empty = (count == 0);
    assign almost_full = (count >= active_watermark);
    assign almost_empty = (count <= (DEPTH/4)); // Default 25%
    assign level = count;

    always @(posedge clk or negedge rst_n) begin
        if (!rst_n) begin
            count    <= 0;
            wr_ptr   <= 0;
            rd_ptr   <= 0;
            overflow <= 0;
            rd_data  <= 0;
            rd_valid <= 0;
        end else begin
            rd_valid <= 1'b0;

            if (csr_en && csr_flush) begin
                count  <= 0;
                wr_ptr <= 0;
                rd_ptr <= 0;
            end else begin
                // Handle read
                if (rd_en && !empty) begin
                    rd_data  <= ram[rd_ptr];
                    rd_valid <= 1'b1;
                    rd_ptr   <= rd_ptr + 1;
                end
                
                // Handle write
                if (wr_en) begin
                    if (!full) begin
                        ram[wr_ptr] <= wr_data;
                        wr_ptr <= wr_ptr + 1;
                    end else begin
                        overflow <= 1'b1; // Sticky flag
                    end
                end
                
                // Count update
                case ({wr_en && !full, rd_en && !empty})
                    2'b10: count <= count + 1;
                    2'b01: count <= count - 1;
                    default: count <= count;
                endcase
            end

            // Clear sticky overflow flag
            if (csr_en && csr_clear_overflow) begin
                overflow <= 1'b0;
            end
        end
    end

endmodule

tb/tb_fifo.v
`timescale 1ns / 1ps

module tb_fifo;

    reg clk;
    reg rst_n;
    reg csr_en;
    reg csr_flush;
    reg csr_clear_overflow;
    reg [10:0] csr_watermark;
    reg [7:0] wr_data;
    reg wr_en;
    reg rd_en;

    wire [7:0] rd_data;
    wire full;
    wire empty;
    wire almost_full;
    wire almost_empty;
    wire overflow;
    wire [11:0] level;

    fifo_sync #(
        .DATA_WIDTH(8),
        .DEPTH_LOG2(11) // 2048 elements
    ) uut (
        .clk(clk),
        .rst_n(rst_n),
        .csr_en(csr_en),
        .csr_flush(csr_flush),
        .csr_clear_overflow(csr_clear_overflow),
        .csr_watermark(csr_watermark),
        .wr_data(wr_data),
        .wr_en(wr_en),
        .rd_en(rd_en),
        .rd_data(rd_data),
        .full(full),
        .empty(empty),
        .almost_full(almost_full),
        .almost_empty(almost_empty),
        .overflow(overflow),
        .level(level)
    );

    always #5 clk = ~clk;

    integer i;

    initial begin
        $dumpfile("sim/tb_fifo.vcd");
        $dumpvars(0, tb_fifo);
        clk = 0;
        rst_n = 0;
        csr_en = 0;
        csr_flush = 0;
        csr_clear_overflow = 0;
        csr_watermark = 1536; // 75%
        wr_data = 0;
        wr_en = 0;
        rd_en = 0;

        #20 rst_n = 1;

        if (empty) $display("PASS: FIFO is initially empty");

        // Fill FIFO
        $display("Filling FIFO with 2048 bytes...");
        for (i = 0; i < 2048; i = i + 1) begin
            @(posedge clk);
            wr_data <= i[7:0];
            wr_en <= 1;
        end
        @(posedge clk);
        wr_en <= 0;
        
        // Wait one cycle for flags to settle
        @(posedge clk);

        if (full) $display("PASS: FIFO reports full");
        else $display("FAIL: FIFO not full");
        
        if (almost_full) $display("PASS: FIFO reports almost full");

        // Trigger overflow
        @(posedge clk);
        wr_data <= 8'hFF;
        wr_en <= 1;
        @(posedge clk);
        wr_en <= 0;
        @(posedge clk);
        if (overflow) $display("PASS: Overflow flag triggered");
        else $display("FAIL: No overflow detected");

        // Empty FIFO
        $display("Reading 2048 bytes from FIFO...");
        rd_en <= 1;
        for (i = 0; i < 2048; i = i + 1) begin
            @(posedge clk);
            // rd_data is available on the next cycle, so verify it carefully
        end
        rd_en <= 0;
        
        @(posedge clk);
        @(posedge clk); // Give extra cycle for count to reach 0

        if (empty) $display("PASS: FIFO reports empty again");
        else $display("FAIL: FIFO not empty. Level is %d", level);

        #20 $finish;
    end

endmodule

sim/tb_fifo.vcd
$date
	Sat Apr 25 08:30:00 2026
$end
$version
	Icarus Verilog
$end
$timescale
	1ps
$end
$scope module tb_fifo $end
$var wire 8 ! rd_data [7:0] $end
$var wire 1 " overflow $end
$var wire 12 # level [11:0] $end
$var wire 1 $ full $end
$var wire 1 % empty $end
$var wire 1 & almost_full $end
$var wire 1 ' almost_empty $end
$var reg 1 ( clk $end
$var reg 1 ) csr_clear_overflow $end
$var reg 1 * csr_en $end
$var reg 1 + csr_flush $end
$var reg 11 , csr_watermark [10:0] $end
$var reg 1 - rd_en $end
$var reg 1 . rst_n $end
$var reg 8 / wr_data [7:0] $end
$var reg 1 0 wr_en $end
$var integer 32 1 i [31:0] $end
$scope module uut $end
$var wire 1 ( clk $end
$var wire 1 ) csr_clear_overflow $end
$var wire 1 * csr_en $end
$var wire 1 + csr_flush $end
$var wire 11 2 csr_watermark [10:0] $end
$var wire 12 3 level [11:0] $end
$var wire 1 - rd_en $end
$var wire 1 . rst_n $end
$var wire 8 4 wr_data [7:0] $end
$var wire 1 0 wr_en $end
$var wire 1 $ full $end
$var wire 1 % empty $end
$var wire 1 & almost_full $end
$var wire 1 ' almost_empty $end
$var wire 11 5 active_watermark [10:0] $end
$var parameter 32 6 DATA_WIDTH $end
$var parameter 43 7 DEPTH $end
$var parameter 32 8 DEPTH_LOG2 $end
$var reg 12 9 count [11:0] $end
$var reg 1 " overflow $end
$var reg 8 : rd_data [7:0] $end
$var reg 11 ; rd_ptr [10:0] $end
$var reg 1 < rd_valid $end
$var reg 11 = wr_ptr [10:0] $end
$upscope $end
$upscope $end
$enddefinitions $end
$comment Show the parameter values. $end
$dumpall
b1011 8
b100000000000 7
b1000 6
$end
#0
$dumpvars
b0 =
0<
b0 ;
b0 :
b0 9
b11000000000 5
b0 4
b0 3
b11000000000 2
bx 1
00
b0 /
0.
0-
b11000000000 ,
0+
0*
0)
0(
1'
0&
1%
0$
b0 #
0"
b0 !
$end
#5000
1(
#10000
0(
#15000
1(
#20000
0(
b0 1
1.
#25000
10
b1 1
1(
#30000
0(
#35000
0%
b1 #
b1 3
b1 9
b1 =
b1 /
b1 4
b10 1
1(
#40000
0(
#45000
b10 #
b10 3
b10 9
b10 =
b10 /
b10 4
b11 1
1(
#50000
0(
#55000
b11 #
b11 3
b11 9
b11 =
b11 /
b11 4
b100 1
1(
#60000
0(
#65000
b100 #
b100 3
b100 9
b100 =
b100 /
b100 4
b101 1
1(
#70000
0(
#75000
b101 #
b101 3
b101 9
b101 =
b101 /
b101 4
b110 1
1(
#80000
0(
#85000
b110 #
b110 3
b110 9
b110 =
b110 /
b110 4
b111 1
1(
#90000
0(
#95000
b111 #
b111 3
b111 9
b111 =
b111 /
b111 4
b1000 1
1(
#100000
0(
#105000
b1000 #
b1000 3
b1000 9
b1000 =
b1000 /
b1000 4
b1001 1
1(
#110000
0(
#115000
b1001 #
b1001 3
b1001 9
b1001 =
b1001 /
b1001 4
b1010 1
1(
#120000
0(
#125000
b1010 #
b1010 3
b1010 9
b1010 =
b1010 /
b1010 4
b1011 1
1(
#130000
0(
#135000
b1011 #
b1011 3
b1011 9
b1011 =
b1011 /
b1011 4
b1100 1
1(
#140000
0(
#145000
b1100 #
b1100 3
b1100 9
b1100 =
b1100 /
b1100 4
b1101 1
1(
#150000
0(
#155000
b1101 #
b1101 3
b1101 9
b1101 =
b1101 /
b1101 4
b1110 1
1(
#160000
0(
#165000
b1110 #
b1110 3
b1110 9
b1110 =
b1110 /
b1110 4
b1111 1
1(
#170000
0(
#175000
b1111 #
b1111 3
b1111 9
b1111 =
b1111 /
b1111 4
b10000 1
1(
#180000
0(
#185000
b10000 #
b10000 3
b10000 9
b10000 =
b10000 /
b10000 4
b10001 1
1(
#190000
0(
#195000
b10001 #
b10001 3
b10001 9
b10001 =
b10001 /
b10001 4
b10010 1
1(
#200000
0(
#205000
b10010 #
b10010 3
b10010 9
b10010 =
b10010 /
b10010 4
b10011 1
1(
#210000
0(
#215000
b10011 #
b10011 3
b10011 9
b10011 =
b10011 /
b10011 4
b10100 1
1(
#220000
0(
#225000
b10100 #
b10100 3
b10100 9
b10100 =
b10100 /
b10100 4
b10101 1
1(
#230000
0(
#235000
b10101 #
b10101 3
b10101 9
b10101 =
b10101 /
b10101 4
b10110 1
1(
#240000
0(
#245000
b10110 #
b10110 3
b10110 9
b10110 =
b10110 /
b10110 4
b10111 1
1(
#250000
0(
#255000
b10111 #
b10111 3
b10111 9
b10111 =
b10111 /
b10111 4
b11000 1
1(
#260000
0(
#265000
b11000 #
b11000 3
b11000 9
b11000 =
b11000 /
b11000 4
b11001 1
1(
#270000
0(
#275000
b11001 #
b11001 3
b11001 9
b11001 =
b11001 /
b11001 4
b11010 1
1(
#280000
0(
#285000
b11010 #
b11010 3
b11010 9
b11010 =
b11010 /
b11010 4
b11011 1
1(
#290000
0(
#295000
b11011 #
b11011 3
b11011 9
b11011 =
b11011 /
b11011 4
b11100 1
1(
#300000
0(
#305000
b11100 #
b11100 3
b11100 9
b11100 =
b11100 /
b11100 4
b11101 1
1(
#310000
0(
#315000
b11101 #
b11101 3
b11101 9
b11101 =
b11101 /
b11101 4
b11110 1
1(
#320000
0(
#325000
b11110 #
b11110 3
b11110 9
b11110 =
b11110 /
b11110 4
b11111 1
1(
#330000
0(
#335000
b11111 #
b11111 3
b11111 9
b11111 =
b11111 /
b11111 4
b100000 1
1(
#340000
0(
#345000
b100000 #
b100000 3
b100000 9
b100000 =
b100000 /
b100000 4
b100001 1
1(
#350000
0(
#355000
b100001 #
b100001 3
b100001 9
b100001 =
b100001 /
b100001 4
b100010 1
1(
#360000
0(
#365000
b100010 #
b100010 3
b100010 9
b100010 =
b100010 /
b100010 4
b100011 1
1(
#370000
0(
#375000
b100011 #
b100011 3
b100011 9
b100011 =
b100011 /
b100011 4
b100100 1
1(
#380000
0(
#385000
b100100 #
b100100 3
b100100 9
b100100 =
b100100 /
b100100 4
b100101 1
1(
#390000
0(
#395000
b100101 #
b100101 3
b100101 9
b100101 =
b100101 /
b100101 4
b100110 1
1(
#400000
0(
#405000
b100110 #
b100110 3
b100110 9
b100110 =
b100110 /
b100110 4
b100111 1
1(
#410000
0(
#415000
b100111 #
b100111 3
b100111 9
b100111 =
b100111 /
b100111 4
b101000 1
1(
#420000
0(
#425000
b101000 #
b101000 3
b101000 9
b101000 =
b101000 /
b101000 4
b101001 1
1(
#430000
0(
#435000
b101001 #
b101001 3
b101001 9
b101001 =
b101001 /
b101001 4
b101010 1
1(
#440000
0(
#445000
b101010 #
b101010 3
b101010 9
b101010 =
b101010 /
b101010 4
b101011 1
1(
#450000
0(
#455000
b101011 #
b101011 3
b101011 9
b101011 =
b101011 /
b101011 4
b101100 1
1(
#460000
0(
#465000
b101100 #
b101100 3
b101100 9
b101100 =
b101100 /
b101100 4
b101101 1
1(
#470000
0(
#475000
b101101 #
b101101 3
b101101 9
b101101 =
b101101 /
b101101 4
b101110 1
1(
#480000
0(
#485000
b101110 #
b101110 3
b101110 9
b101110 =
b101110 /
b101110 4
b101111 1
1(
#490000
0(
#495000
b101111 #
b101111 3
b101111 9
b101111 =
b101111 /
b101111 4
b110000 1
1(
#500000
0(
#505000
b110000 #
b110000 3
b110000 9
b110000 =
b110000 /
b110000 4
b110001 1
1(
#510000
0(
#515000
b110001 #
b110001 3
b110001 9
b110001 =
b110001 /
b110001 4
b110010 1
1(
#520000
0(
#525000
b110010 #
b110010 3
b110010 9
b110010 =
b110010 /
b110010 4
b110011 1
1(
#530000
0(
#535000
b110011 #
b110011 3
b110011 9
b110011 =
b110011 /
b110011 4
b110100 1
1(
#540000
0(
#545000
b110100 #
b110100 3
b110100 9
b110100 =
b110100 /
b110100 4
b110101 1
1(
#550000
0(
#555000
b110101 #
b110101 3
b110101 9
b110101 =
b110101 /
b110101 4
b110110 1
1(
#560000
0(
#565000
b110110 #
b110110 3
b110110 9
b110110 =
b110110 /
b110110 4
b110111 1
1(
#570000
0(
#575000
b110111 #
b110111 3
b110111 9
b110111 =
b110111 /
b110111 4
b111000 1
1(
#580000
0(
#585000
b111000 #
b111000 3
b111000 9
b111000 =
b111000 /
b111000 4
b111001 1
1(
#590000
0(
#595000
b111001 #
b111001 3
b111001 9
b111001 =
b111001 /
b111001 4
b111010 1
1(
#600000
0(
#605000
b111010 #
b111010 3
b111010 9
b111010 =
b111010 /
b111010 4
b111011 1
1(
#610000
0(
#615000
b111011 #
b111011 3
b111011 9
b111011 =
b111011 /
b111011 4
b111100 1
1(
#620000
0(
#625000
b111100 #
b111100 3
b111100 9
b111100 =
b111100 /
b111100 4
b111101 1
1(
#630000
0(
#635000
b111101 #
b111101 3
b111101 9
b111101 =
b111101 /
b111101 4
b111110 1
1(
#640000
0(
#645000
b111110 #
b111110 3
b111110 9
b111110 =
b111110 /
b111110 4
b111111 1
1(
#650000
0(
#655000
b111111 #
b111111 3
b111111 9
b111111 =
b111111 /
b111111 4
b1000000 1
1(
#660000
0(
#665000
b1000000 #
b1000000 3
b1000000 9
b1000000 =
b1000000 /
b1000000 4
b1000001 1
1(
#670000
0(
#675000
b1000001 #
b1000001 3
b1000001 9
b1000001 =
b1000001 /
b1000001 4
b1000010 1
1(
#680000
0(
#685000
b1000010 #
b1000010 3
b1000010 9
b1000010 =
b1000010 /
b1000010 4
b1000011 1
1(
#690000
0(
#695000
b1000011 #
b1000011 3
b1000011 9
b1000011 =
b1000011 /
b1000011 4
b1000100 1
1(
#700000
0(
#705000
b1000100 #
b1000100 3
b1000100 9
b1000100 =
b1000100 /
b1000100 4
b1000101 1
1(
#710000
0(
#715000
b1000101 #
b1000101 3
b1000101 9
b1000101 =
b1000101 /
b1000101 4
b1000110 1
1(
#720000
0(
#725000
b1000110 #
b1000110 3
b1000110 9
b1000110 =
b1000110 /
b1000110 4
b1000111 1
1(
#730000
0(
#735000
b1000111 #
b1000111 3
b1000111 9
b1000111 =
b1000111 /
b1000111 4
b1001000 1
1(
#740000
0(
#745000
b1001000 #
b1001000 3
b1001000 9
b1001000 =
b1001000 /
b1001000 4
b1001001 1
1(
#750000
0(
#755000
b1001001 #
b1001001 3
b1001001 9
b1001001 =
b1001001 /
b1001001 4
b1001010 1
1(
#760000
0(
#765000
b1001010 #
b1001010 3
b1001010 9
b1001010 =
b1001010 /
b1001010 4
b1001011 1
1(
#770000
0(
#775000
b1001011 #
b1001011 3
b1001011 9
b1001011 =
b1001011 /
b1001011 4
b1001100 1
1(
#780000
0(
#785000
b1001100 #
b1001100 3
b1001100 9
b1001100 =
b1001100 /
b1001100 4
b1001101 1
1(
#790000
0(
#795000
b1001101 #
b1001101 3
b1001101 9
b1001101 =
b1001101 /
b1001101 4
b1001110 1
1(
#800000
0(
#805000
b1001110 #
b1001110 3
b1001110 9
b1001110 =
b1001110 /
b1001110 4
b1001111 1
1(
#810000
0(
#815000
b1001111 #
b1001111 3
b1001111 9
b1001111 =
b1001111 /
b1001111 4
b1010000 1
1(
#820000
0(
#825000
b1010000 #
b1010000 3
b1010000 9
b1010000 =
b1010000 /
b1010000 4
b1010001 1
1(
#830000
0(
#835000
b1010001 #
b1010001 3
b1010001 9
b1010001 =
b1010001 /
b1010001 4
b1010010 1
1(
#840000
0(
#845000
b1010010 #
b1010010 3
b1010010 9
b1010010 =
b1010010 /
b1010010 4
b1010011 1
1(
#850000
0(
#855000
b1010011 #
b1010011 3
b1010011 9
b1010011 =
b1010011 /
b1010011 4
b1010100 1
1(
#860000
0(
#865000
b1010100 #
b1010100 3
b1010100 9
b1010100 =
b1010100 /
b1010100 4
b1010101 1
1(
#870000
0(
#875000
b1010101 #
b1010101 3
b1010101 9
b1010101 =
b1010101 /
b1010101 4
b1010110 1
1(
#880000
0(
#885000
b1010110 #
b1010110 3
b1010110 9
b1010110 =
b1010110 /
b1010110 4
b1010111 1
1(
#890000
0(
#895000
b1010111 #
b1010111 3
b1010111 9
b1010111 =
b1010111 /
b1010111 4
b1011000 1
1(
#900000
0(
#905000
b1011000 #
b1011000 3
b1011000 9
b1011000 =
b1011000 /
b1011000 4
b1011001 1
1(
#910000
0(
#915000
b1011001 #
b1011001 3
b1011001 9
b1011001 =
b1011001 /
b1011001 4
b1011010 1
1(
#920000
0(
#925000
b1011010 #
b1011010 3
b1011010 9
b1011010 =
b1011010 /
b1011010 4
b1011011 1
1(
#930000
0(
#935000
b1011011 #
b1011011 3
b1011011 9
b1011011 =
b1011011 /
b1011011 4
b1011100 1
1(
#940000
0(
#945000
b1011100 #
b1011100 3
b1011100 9
b1011100 =
b1011100 /
b1011100 4
b1011101 1
1(
#950000
0(
#955000
b1011101 #
b1011101 3
b1011101 9
b1011101 =
b1011101 /
b1011101 4
b1011110 1
1(
#960000
0(
#965000
b1011110 #
b1011110 3
b1011110 9
b1011110 =
b1011110 /
b1011110 4
b1011111 1
1(
#970000
0(
#975000
b1011111 #
b1011111 3
b1011111 9
b1011111 =
b1011111 /
b1011111 4
b1100000 1
1(
#980000
0(
#985000
b1100000 #
b1100000 3
b1100000 9
b1100000 =
b1100000 /
b1100000 4
b1100001 1
1(
#990000
0(
#995000
b1100001 #
b1100001 3
b1100001 9
b1100001 =
b1100001 /
b1100001 4
b1100010 1
1(
#1000000
0(
#1005000
b1100010 #
b1100010 3
b1100010 9
b1100010 =
b1100010 /
b1100010 4
b1100011 1
1(
#1010000
0(
#1015000
b1100011 #
b1100011 3
b1100011 9
b1100011 =
b1100011 /
b1100011 4
b1100100 1
1(
#1020000
0(
#1025000
b1100100 #
b1100100 3
b1100100 9
b1100100 =
b1100100 /
b1100100 4
b1100101 1
1(
#1030000
0(
#1035000
b1100101 #
b1100101 3
b1100101 9
b1100101 =
b1100101 /
b1100101 4
b1100110 1
1(
#1040000
0(
#1045000
b1100110 #
b1100110 3
b1100110 9
b1100110 =
b1100110 /
b1100110 4
b1100111 1
1(
#1050000
0(
#1055000
b1100111 #
b1100111 3
b1100111 9
b1100111 =
b1100111 /
b1100111 4
b1101000 1
1(
#1060000
0(
#1065000
b1101000 #
b1101000 3
b1101000 9
b1101000 =
b1101000 /
b1101000 4
b1101001 1
1(
#1070000
0(
#1075000
b1101001 #
b1101001 3
b1101001 9
b1101001 =
b1101001 /
b1101001 4
b1101010 1
1(
#1080000
0(
#1085000
b1101010 #
b1101010 3
b1101010 9
b1101010 =
b1101010 /
b1101010 4
b1101011 1
1(
#1090000
0(
#1095000
b1101011 #
b1101011 3
b1101011 9
b1101011 =
b1101011 /
b1101011 4
b1101100 1
1(
#1100000
0(
#1105000
b1101100 #
b1101100 3
b1101100 9
b1101100 =
b1101100 /
b1101100 4
b1101101 1
1(
#1110000
0(
#1115000
b1101101 #
b1101101 3
b1101101 9
b1101101 =
b1101101 /
b1101101 4
b1101110 1
1(
#1120000
0(
#1125000
b1101110 #
b1101110 3
b1101110 9
b1101110 =
b1101110 /
b1101110 4
b1101111 1
1(
#1130000
0(
#1135000
b1101111 #
b1101111 3
b1101111 9
b1101111 =
b1101111 /
b1101111 4
b1110000 1
1(
#1140000
0(
#1145000
b1110000 #
b1110000 3
b1110000 9
b1110000 =
b1110000 /
b1110000 4
b1110001 1
1(
#1150000
0(
#1155000
b1110001 #
b1110001 3
b1110001 9
b1110001 =
b1110001 /
b1110001 4
b1110010 1
1(
#1160000
0(
#1165000
b1110010 #
b1110010 3
b1110010 9
b1110010 =
b1110010 /
b1110010 4
b1110011 1
1(
#1170000
0(
#1175000
b1110011 #
b1110011 3
b1110011 9
b1110011 =
b1110011 /
b1110011 4
b1110100 1
1(
#1180000
0(
#1185000
b1110100 #
b1110100 3
b1110100 9
b1110100 =
b1110100 /
b1110100 4
b1110101 1
1(
#1190000
0(
#1195000
b1110101 #
b1110101 3
b1110101 9
b1110101 =
b1110101 /
b1110101 4
b1110110 1
1(
#1200000
0(
#1205000
b1110110 #
b1110110 3
b1110110 9
b1110110 =
b1110110 /
b1110110 4
b1110111 1
1(
#1210000
0(
#1215000
b1110111 #
b1110111 3
b1110111 9
b1110111 =
b1110111 /
b1110111 4
b1111000 1
1(
#1220000
0(
#1225000
b1111000 #
b1111000 3
b1111000 9
b1111000 =
b1111000 /
b1111000 4
b1111001 1
1(
#1230000
0(
#1235000
b1111001 #
b1111001 3
b1111001 9
b1111001 =
b1111001 /
b1111001 4
b1111010 1
1(
#1240000
0(
#1245000
b1111010 #
b1111010 3
b1111010 9
b1111010 =
b1111010 /
b1111010 4
b1111011 1
1(
#1250000
0(
#1255000
b1111011 #
b1111011 3
b1111011 9
b1111011 =
b1111011 /
b1111011 4
b1111100 1
1(
#1260000
0(
#1265000
b1111100 #
b1111100 3
b1111100 9
b1111100 =
b1111100 /
b1111100 4
b1111101 1
1(
#1270000
0(
#1275000
b1111101 #
b1111101 3
b1111101 9
b1111101 =
b1111101 /
b1111101 4
b1111110 1
1(
#1280000
0(
#1285000
b1111110 #
b1111110 3
b1111110 9
b1111110 =
b1111110 /
b1111110 4
b1111111 1
1(
#1290000
0(
#1295000
b1111111 #
b1111111 3
b1111111 9
b1111111 =
b1111111 /
b1111111 4
b10000000 1
1(
#1300000
0(
#1305000
b10000000 #
b10000000 3
b10000000 9
b10000000 =
b10000000 /
b10000000 4
b10000001 1
1(
#1310000
0(
#1315000
b10000001 #
b10000001 3
b10000001 9
b10000001 =
b10000001 /
b10000001 4
b10000010 1
1(
#1320000
0(
#1325000
b10000010 #
b10000010 3
b10000010 9
b10000010 =
b10000010 /
b10000010 4
b10000011 1
1(
#1330000
0(
#1335000
b10000011 #
b10000011 3
b10000011 9
b10000011 =
b10000011 /
b10000011 4
b10000100 1
1(
#1340000
0(
#1345000
b10000100 #
b10000100 3
b10000100 9
b10000100 =
b10000100 /
b10000100 4
b10000101 1
1(
#1350000
0(
#1355000
b10000101 #
b10000101 3
b10000101 9
b10000101 =
b10000101 /
b10000101 4
b10000110 1
1(
#1360000
0(
#1365000
b10000110 #
b10000110 3
b10000110 9
b10000110 =
b10000110 /
b10000110 4
b10000111 1
1(
#1370000
0(
#1375000
b10000111 #
b10000111 3
b10000111 9
b10000111 =
b10000111 /
b10000111 4
b10001000 1
1(
#1380000
0(
#1385000
b10001000 #
b10001000 3
b10001000 9
b10001000 =
b10001000 /
b10001000 4
b10001001 1
1(
#1390000
0(
#1395000
b10001001 #
b10001001 3
b10001001 9
b10001001 =
b10001001 /
b10001001 4
b10001010 1
1(
#1400000
0(
#1405000
b10001010 #
b10001010 3
b10001010 9
b10001010 =
b10001010 /
b10001010 4
b10001011 1
1(
#1410000
0(
#1415000
b10001011 #
b10001011 3
b10001011 9
b10001011 =
b10001011 /
b10001011 4
b10001100 1
1(
#1420000
0(
#1425000
b10001100 #
b10001100 3
b10001100 9
b10001100 =
b10001100 /
b10001100 4
b10001101 1
1(
#1430000
0(
#1435000
b10001101 #
b10001101 3
b10001101 9
b10001101 =
b10001101 /
b10001101 4
b10001110 1
1(
#1440000
0(
#1445000
b10001110 #
b10001110 3
b10001110 9
b10001110 =
b10001110 /
b10001110 4
b10001111 1
1(
#1450000
0(
#1455000
b10001111 #
b10001111 3
b10001111 9
b10001111 =
b10001111 /
b10001111 4
b10010000 1
1(
#1460000
0(
#1465000
b10010000 #
b10010000 3
b10010000 9
b10010000 =
b10010000 /
b10010000 4
b10010001 1
1(
#1470000
0(
#1475000
b10010001 #
b10010001 3
b10010001 9
b10010001 =
b10010001 /
b10010001 4
b10010010 1
1(
#1480000
0(
#1485000
b10010010 #
b10010010 3
b10010010 9
b10010010 =
b10010010 /
b10010010 4
b10010011 1
1(
#1490000
0(
#1495000
b10010011 #
b10010011 3
b10010011 9
b10010011 =
b10010011 /
b10010011 4
b10010100 1
1(
#1500000
0(
#1505000
b10010100 #
b10010100 3
b10010100 9
b10010100 =
b10010100 /
b10010100 4
b10010101 1
1(
#1510000
0(
#1515000
b10010101 #
b10010101 3
b10010101 9
b10010101 =
b10010101 /
b10010101 4
b10010110 1
1(
#1520000
0(
#1525000
b10010110 #
b10010110 3
b10010110 9
b10010110 =
b10010110 /
b10010110 4
b10010111 1
1(
#1530000
0(
#1535000
b10010111 #
b10010111 3
b10010111 9
b10010111 =
b10010111 /
b10010111 4
b10011000 1
1(
#1540000
0(
#1545000
b10011000 #
b10011000 3
b10011000 9
b10011000 =
b10011000 /
b10011000 4
b10011001 1
1(
#1550000
0(
#1555000
b10011001 #
b10011001 3
b10011001 9
b10011001 =
b10011001 /
b10011001 4
b10011010 1
1(
#1560000
0(
#1565000
b10011010 #
b10011010 3
b10011010 9
b10011010 =
b10011010 /
b10011010 4
b10011011 1
1(
#1570000
0(
#1575000
b10011011 #
b10011011 3
b10011011 9
b10011011 =
b10011011 /
b10011011 4
b10011100 1
1(
#1580000
0(
#1585000
b10011100 #
b10011100 3
b10011100 9
b10011100 =
b10011100 /
b10011100 4
b10011101 1
1(
#1590000
0(
#1595000
b10011101 #
b10011101 3
b10011101 9
b10011101 =
b10011101 /
b10011101 4
b10011110 1
1(
#1600000
0(
#1605000
b10011110 #
b10011110 3
b10011110 9
b10011110 =
b10011110 /
b10011110 4
b10011111 1
1(
#1610000
0(
#1615000
b10011111 #
b10011111 3
b10011111 9
b10011111 =
b10011111 /
b10011111 4
b10100000 1
1(
#1620000
0(
#1625000
b10100000 #
b10100000 3
b10100000 9
b10100000 =
b10100000 /
b10100000 4
b10100001 1
1(
#1630000
0(
#1635000
b10100001 #
b10100001 3
b10100001 9
b10100001 =
b10100001 /
b10100001 4
b10100010 1
1(
#1640000
0(
#1645000
b10100010 #
b10100010 3
b10100010 9
b10100010 =
b10100010 /
b10100010 4
b10100011 1
1(
#1650000
0(
#1655000
b10100011 #
b10100011 3
b10100011 9
b10100011 =
b10100011 /
b10100011 4
b10100100 1
1(
#1660000
0(
#1665000
b10100100 #
b10100100 3
b10100100 9
b10100100 =
b10100100 /
b10100100 4
b10100101 1
1(
#1670000
0(
#1675000
b10100101 #
b10100101 3
b10100101 9
b10100101 =
b10100101 /
b10100101 4
b10100110 1
1(
#1680000
0(
#1685000
b10100110 #
b10100110 3
b10100110 9
b10100110 =
b10100110 /
b10100110 4
b10100111 1
1(
#1690000
0(
#1695000
b10100111 #
b10100111 3
b10100111 9
b10100111 =
b10100111 /
b10100111 4
b10101000 1
1(
#1700000
0(
#1705000
b10101000 #
b10101000 3
b10101000 9
b10101000 =
b10101000 /
b10101000 4
b10101001 1
1(
#1710000
0(
#1715000
b10101001 #
b10101001 3
b10101001 9
b10101001 =
b10101001 /
b10101001 4
b10101010 1
1(
#1720000
0(
#1725000
b10101010 #
b10101010 3
b10101010 9
b10101010 =
b10101010 /
b10101010 4
b10101011 1
1(
#1730000
0(
#1735000
b10101011 #
b10101011 3
b10101011 9
b10101011 =
b10101011 /
b10101011 4
b10101100 1
1(
#1740000
0(
#1745000
b10101100 #
b10101100 3
b10101100 9
b10101100 =
b10101100 /
b10101100 4
b10101101 1
1(
#1750000
0(
#1755000
b10101101 #
b10101101 3
b10101101 9
b10101101 =
b10101101 /
b10101101 4
b10101110 1
1(
#1760000
0(
#1765000
b10101110 #
b10101110 3
b10101110 9
b10101110 =
b10101110 /
b10101110 4
b10101111 1
1(
#1770000
0(
#1775000
b10101111 #
b10101111 3
b10101111 9
b10101111 =
b10101111 /
b10101111 4
b10110000 1
1(
#1780000
0(
#1785000
b10110000 #
b10110000 3
b10110000 9
b10110000 =
b10110000 /
b10110000 4
b10110001 1
1(
#1790000
0(
#1795000
b10110001 #
b10110001 3
b10110001 9
b10110001 =
b10110001 /
b10110001 4
b10110010 1
1(
#1800000
0(
#1805000
b10110010 #
b10110010 3
b10110010 9
b10110010 =
b10110010 /
b10110010 4
b10110011 1
1(
#1810000
0(
#1815000
b10110011 #
b10110011 3
b10110011 9
b10110011 =
b10110011 /
b10110011 4
b10110100 1
1(
#1820000
0(
#1825000
b10110100 #
b10110100 3
b10110100 9
b10110100 =
b10110100 /
b10110100 4
b10110101 1
1(
#1830000
0(
#1835000
b10110101 #
b10110101 3
b10110101 9
b10110101 =
b10110101 /
b10110101 4
b10110110 1
1(
#1840000
0(
#1845000
b10110110 #
b10110110 3
b10110110 9
b10110110 =
b10110110 /
b10110110 4
b10110111 1
1(
#1850000
0(
#1855000
b10110111 #
b10110111 3
b10110111 9
b10110111 =
b10110111 /
b10110111 4
b10111000 1
1(
#1860000
0(
#1865000
b10111000 #
b10111000 3
b10111000 9
b10111000 =
b10111000 /
b10111000 4
b10111001 1
1(
#1870000
0(
#1875000
b10111001 #
b10111001 3
b10111001 9
b10111001 =
b10111001 /
b10111001 4
b10111010 1
1(
#1880000
0(
#1885000
b10111010 #
b10111010 3
b10111010 9
b10111010 =
b10111010 /
b10111010 4
b10111011 1
1(
#1890000
0(
#1895000
b10111011 #
b10111011 3
b10111011 9
b10111011 =
b10111011 /
b10111011 4
b10111100 1
1(
#1900000
0(
